devEnv/work/prj/src/rtl/entry/midi_uart_rx.v
`timescale 1ns / 1ps
// Simple MIDI UART receiver for 31.25 kbaud streams.
module midi_uart_rx #(
    parameter integer CLK_FREQ_HZ = 100_000_000,
    parameter integer BAUD_RATE   = 31_250
) (
    input  wire clk,
    input  wire rst,
    input  wire rx,
    output reg  [7:0] data_out,
    output reg        data_valid,
    output reg        busy,
    output reg        framing_error
);

    localparam integer CLKS_PER_BIT = CLK_FREQ_HZ / BAUD_RATE;
    localparam integer CTR_WIDTH    = $clog2(CLKS_PER_BIT + 1);

    localparam [2:0] STATE_IDLE  = 3'd0;
    localparam [2:0] STATE_START = 3'd1;
    localparam [2:0] STATE_DATA  = 3'd2;
    localparam [2:0] STATE_STOP  = 3'd3;

    reg [2:0] state;
    reg [CTR_WIDTH-1:0] clk_count;
    reg [2:0] bit_index;
    reg rx_sync0;
    reg rx_sync1;

    // Synchronize RX line to clk domain.
    always @(posedge clk) begin
        rx_sync0 <= rx;
        rx_sync1 <= rx_sync0;
    end

    always @(posedge clk) begin
        if (rst) begin
            state         <= STATE_IDLE;
            clk_count     <= {CTR_WIDTH{1'b0}};
            bit_index     <= 3'd0;
            data_out      <= 8'd0;
            data_valid    <= 1'b0;
            busy          <= 1'b0;
            framing_error <= 1'b0;
        end else begin
            data_valid <= 1'b0;

            case (state)
                STATE_IDLE: begin
                    busy <= 1'b0;
                    if (~rx_sync1) begin // start bit detected
                        busy      <= 1'b1;
                        clk_count <= CLKS_PER_BIT[CTR_WIDTH-1:0] >> 1;
                        state     <= STATE_START;
                    end
                end

                STATE_START: begin
                    if (clk_count == 0) begin
                        if (~rx_sync1) begin
                            clk_count <= CLKS_PER_BIT[CTR_WIDTH-1:0] - 1'b1;
                            bit_index <= 3'd0;
                            state     <= STATE_DATA;
                        end else begin
                            state <= STATE_IDLE; // false start
                        end
                    end else begin
                        clk_count <= clk_count - 1'b1;
                    end
                end

                STATE_DATA: begin
                    if (clk_count == 0) begin
                        data_out[bit_index] <= rx_sync1;
                        clk_count           <= CLKS_PER_BIT[CTR_WIDTH-1:0] - 1'b1;
                        if (bit_index == 3'd7) begin
                            state <= STATE_STOP;
                        end else begin
                            bit_index <= bit_index + 1'b1;
                        end
                    end else begin
                        clk_count <= clk_count - 1'b1;
                    end
                end

                STATE_STOP: begin
                    if (clk_count == 0) begin
                        framing_error <= ~rx_sync1;
                        data_valid    <= rx_sync1;
                        state         <= STATE_IDLE;
                    end else begin
                        clk_count <= clk_count - 1'b1;
                    end
                end

                default: state <= STATE_IDLE;
            endcase
        end
    end
endmodule

devEnv/work/project/tb/midi_uart_rx_tb.v
`timescale 1ns / 1ps
//=============================================================================
// File         : midi_uart_rx_tb.v
// Author       : Mateo Almeida
// Description  :
//   Testbench for the midi_uart_rx module. This testbench verifies correct
//   reception of MIDI UART data at the standard MIDI baud rate (31.25 kbaud).
//
//   The testbench:
//     - Generates a system clock
//     - Applies a reset sequence
//     - Simulates UART serial input on the rx line
//     - Sends example MIDI bytes (Note On and Control Change)
//     - Dumps waveform data for offline analysis
//
//   The UART framing follows standard 8-N-1 format:
//     - 1 start bit (0)
//     - 8 data bits (LSB first)
//     - 1 stop bit (1)
//
//   Waveform output is written to:
//     sim/build/midi_uart_rx_tb.vcd
//
//=============================================================================

module midi_uart_rx_tb;

    //-------------------------------------------------------------------------
    // Testbench parameters
    //-------------------------------------------------------------------------
    localparam integer CLK_FREQ_HZ = 10_000_000; // 10 MHz system clock
    localparam integer BAUD_RATE   = 31_250;     // Standard MIDI baud rate
    localparam integer CLK_PERIOD  = 100;        // Clock period in ns (10 MHz)
    localparam integer BIT_PERIOD  = 32_000;     // UART bit period in ns

    //-------------------------------------------------------------------------
    // Testbench signals
    //-------------------------------------------------------------------------
    reg clk = 1'b0;
    reg rst = 1'b1;
    reg rx  = 1'b1; // UART idle state is logic high

    wire [7:0] data_out;
    wire       data_valid;
    wire       busy;
    wire       framing_error;

    //-------------------------------------------------------------------------
    // Clock generation
    //-------------------------------------------------------------------------
    always #(CLK_PERIOD/2) clk = ~clk;

    //-------------------------------------------------------------------------
    // Device Under Test (DUT)
    //-------------------------------------------------------------------------
    midi_uart_rx #(
        .CLK_FREQ_HZ(CLK_FREQ_HZ),
        .BAUD_RATE  (BAUD_RATE)
    ) dut (
        .clk           (clk),
        .rst           (rst),
        .rx            (rx),
        .data_out      (data_out),
        .data_valid    (data_valid),
        .busy          (busy),
        .framing_error (framing_error)
    );

    //-------------------------------------------------------------------------
    // Waveform dump configuration
    //-------------------------------------------------------------------------
    initial begin
        // Dumpfile stored in sim/build directory for easy access
        $dumpfile("sim/build/midi_uart_rx_tb.vcd");
        $dumpvars(0, midi_uart_rx_tb);
    end

    //-------------------------------------------------------------------------
    // Task: send_byte
    // Description:
    //   Sends one UART-formatted byte on the rx line using:
    //     - 1 start bit
    //     - 8 data bits (LSB first)
    //     - 1 stop bit
    //-------------------------------------------------------------------------
    task send_byte(input [7:0] value);
        integer i;
        begin
            // Start bit
            rx <= 1'b0;
            #(BIT_PERIOD);

            // Data bits
            for (i = 0; i < 8; i = i + 1) begin
                rx <= value[i];
                #(BIT_PERIOD);
            end

            // Stop bit
            rx <= 1'b1;
            #(BIT_PERIOD);
        end
    endtask

    //-------------------------------------------------------------------------
    // Test sequence
    //-------------------------------------------------------------------------
    initial begin
        // Initial reset period
        #(10*CLK_PERIOD);
        rst <= 1'b0;
        #(10*CLK_PERIOD);

        // Send MIDI Note On message
        send_byte(8'h90); // Note On, channel 0
        send_byte(8'd64); // Velocity
        #(BIT_PERIOD*5);

        // Send MIDI Control Change message
        send_byte(8'hB0); // Control Change, channel 0
        send_byte(8'd100);
        #(BIT_PERIOD*20);

        // End simulation
        $finish;
    end

endmodule

devEnv/work/project/sim/build/midi_uart_rx_tb.vcd
$date
	Mon Nov 10 11:23:31 2025
$end
$version
	Icarus Verilog
$end
$timescale
	1ps
$end
$scope module midi_uart_rx_tb $end
$var wire 1 ! framing_error $end
$var wire 1 " data_valid $end
$var wire 8 # data_out [7:0] $end
$var wire 1 $ busy $end
$var parameter 32 % BAUD_RATE $end
$var parameter 32 & BIT_PERIOD $end
$var parameter 32 ' CLK_FREQ_HZ $end
$var parameter 32 ( CLK_PERIOD $end
$var reg 1 ) clk $end
$var reg 1 * rst $end
$var reg 1 + rx $end
$scope module dut $end
$var wire 1 ) clk $end
$var wire 1 * rst $end
$var wire 1 + rx $end
$var parameter 32 , BAUD_RATE $end
$var parameter 32 - CLKS_PER_BIT $end
$var parameter 32 . CLK_FREQ_HZ $end
$var parameter 32 / CTR_WIDTH $end
$var parameter 3 0 STATE_DATA $end
$var parameter 3 1 STATE_IDLE $end
$var parameter 3 2 STATE_START $end
$var parameter 3 3 STATE_STOP $end
$var reg 3 4 bit_index [2:0] $end
$var reg 1 $ busy $end
$var reg 9 5 clk_count [8:0] $end
$var reg 8 6 data_out [7:0] $end
$var reg 1 " data_valid $end
$var reg 1 ! framing_error $end
$var reg 1 7 rx_sync0 $end
$var reg 1 8 rx_sync1 $end
$var reg 3 9 state [2:0] $end
$upscope $end
$scope task send_byte $end
$var reg 8 : value [7:0] $end
$var integer 32 ; i [31:0] $end
$upscope $end
$upscope $end
$enddefinitions $end
$comment Show the parameter values. $end
$dumpall
b11 3
b1 2
b0 1
b10 0
b1001 /
b100110001001011010000000 .
b101000000 -
b111101000010010 ,
b1100100 (
b100110001001011010000000 '
b111110100000000 &
b111101000010010 %
$end
#0
$dumpvars
bx ;
bx :
bx 9
x8
x7
bx 6
bx 5
bx 4
1+
1*
0)
x$
bx #
x"
x!
$end
#50000
17
0!
0$
0"
b0 #
b0 6
b0 4
b0 5
b0 9
1)
#100000
0)
#150000
18
1)
#200000
0)
#250000
1)
#300000
0)
#350000
1)
#400000
0)
#450000
1)
#500000
0)
#550000
1)
#600000
0)
#650000
1)
#700000
0)
#750000
1)
#800000
0)
#850000
1)
#900000
0)
#950000
1)
#1000000
0*
0)
#1050000
1)
#1100000
0)
#1150000
1)
#1200000
0)
#1250000
1)
#1300000
0)
#1350000
1)
#1400000
0)
#1450000
1)
#1500000
0)
#1550000
1)
#1600000
0)
#1650000
1)
#1700000
0)
#1750000
1)
#1800000
0)
#1850000
1)
#1900000
0)
#1950000
1)
#2000000
0+
0)
b10010000 :
#2050000
07
1)
#2100000
0)
#2150000
08
1)
#2200000
0)
#2250000
b1 9
b10100000 5
1$
1)
#2300000
0)
#2350000
b10011111 5
1)
#2400000
0)
#2450000
b10011110 5
1)
#2500000
0)
#2550000
b10011101 5
1)
#2600000
0)
#2650000
b10011100 5
1)
#2700000
0)
#2750000
b10011011 5
1)
#2800000
0)
#2850000
b10011010 5
1)
#2900000
0)
#2950000
b10011001 5
1)
#3000000
0)
#3050000
b10011000 5
1)
#3100000
0)
#3150000
b10010111 5
1)
#3200000
0)
#3250000
b10010110 5
1)
#3300000
0)
#3350000
b10010101 5
1)
#3400000
0)
#3450000
b10010100 5
1)
#3500000
0)
#3550000
b10010011 5
1)
#3600000
0)
#3650000
b10010010 5
1)
#3700000
0)
#3750000
b10010001 5
1)
#3800000
0)
#3850000
b10010000 5
1)
#3900000
0)
#3950000
b10001111 5
1)
#4000000
0)
#4050000
b10001110 5
1)
#4100000
0)
#4150000
b10001101 5
1)
#4200000
0)
#4250000
b10001100 5
1)
#4300000
0)
#4350000
b10001011 5
1)
#4400000
0)
#4450000
b10001010 5
1)
#4500000
0)
#4550000
b10001001 5
1)
#4600000
0)
#4650000
b10001000 5
1)
#4700000
0)
#4750000
b10000111 5
1)
#4800000
0)
#4850000
b10000110 5
1)
#4900000
0)
#4950000
b10000101 5
1)
#5000000
0)
#5050000
b10000100 5
1)
#5100000
0)
#5150000
b10000011 5
1)
#5200000
0)
#5250000
b10000010 5
1)
#5300000
0)
#5350000
b10000001 5
1)
#5400000
0)
#5450000
b10000000 5
1)
#5500000
0)
#5550000
b1111111 5
1)
#5600000
0)
#5650000
b1111110 5
1)
#5700000
0)
#5750000
b1111101 5
1)
#5800000
0)
#5850000
b1111100 5
1)
#5900000
0)
#5950000
b1111011 5
1)
#6000000
0)
#6050000
b1111010 5
1)
#6100000
0)
#6150000
b1111001 5
1)
#6200000
0)
#6250000
b1111000 5
1)
#6300000
0)
#6350000
b1110111 5
1)
#6400000
0)
#6450000
b1110110 5
1)
#6500000
0)
#6550000
b1110101 5
1)
#6600000
0)
#6650000
b1110100 5
1)
#6700000
0)
#6750000
b1110011 5
1)
#6800000
0)
#6850000
b1110010 5
1)
#6900000
0)
#6950000
b1110001 5
1)
#7000000
0)
#7050000
b1110000 5
1)
#7100000
0)
#7150000
b1101111 5
1)
#7200000
0)
#7250000
b1101110 5
1)
#7300000
0)
#7350000
b1101101 5
1)
#7400000
0)
#7450000
b1101100 5
1)
#7500000
0)
#7550000
b1101011 5
1)
#7600000
0)
#7650000
b1101010 5
1)
#7700000
0)
#7750000
b1101001 5
1)
#7800000
0)
#7850000
b1101000 5
1)
#7900000
0)
#7950000
b1100111 5
1)
#8000000
0)
#8050000
b1100110 5
1)
#8100000
0)
#8150000
b1100101 5
1)
#8200000
0)
#8250000
b1100100 5
1)
#8300000
0)
#8350000
b1100011 5
1)
#8400000
0)
#8450000
b1100010 5
1)
#8500000
0)
#8550000
b1100001 5
1)
#8600000
0)
#8650000
b1100000 5
1)
#8700000
0)
#8750000
b1011111 5
1)
#8800000
0)
#8850000
b1011110 5
1)
#8900000
0)
#8950000
b1011101 5
1)
#9000000
0)
#9050000
b1011100 5
1)
#9100000
0)
#9150000
b1011011 5
1)
#9200000
0)
#9250000
b1011010 5
1)
#9300000
0)
#9350000
b1011001 5
1)
#9400000
0)
#9450000
b1011000 5
1)
#9500000
0)
#9550000
b1010111 5
1)
#9600000
0)
#9650000
b1010110 5
1)
#9700000
0)
#9750000
b1010101 5
1)
#9800000
0)
#9850000
b1010100 5
1)
#9900000
0)
#9950000
b1010011 5
1)
#10000000
0)
#10050000
b1010010 5
1)
#10100000
0)
#10150000
b1010001 5
1)
#10200000
0)
#10250000
b1010000 5
1)
#10300000
0)
#10350000
b1001111 5
1)
#10400000
0)
#10450000
b1001110 5
1)
#10500000
0)
#10550000
b1001101 5
1)
#10600000
0)
#10650000
b1001100 5
1)
#10700000
0)
#10750000
b1001011 5
1)
#10800000
0)
#10850000
b1001010 5
1)
#10900000
0)
#10950000
b1001001 5
1)
#11000000
0)
#11050000
b1001000 5
1)
#11100000
0)
#11150000
b1000111 5
1)
#11200000
0)
#11250000
b1000110 5
1)
#11300000
0)
#11350000
b1000101 5
1)
#11400000
0)
#11450000
b1000100 5
1)
#11500000
0)
#11550000
b1000011 5
1)
#11600000
0)
#11650000
b1000010 5
1)
#11700000
0)
#11750000
b1000001 5
1)
#11800000
0)
#11850000
b1000000 5
1)
#11900000
0)
#11950000
b111111 5
1)
#12000000
0)
#12050000
b111110 5
1)
#12100000
0)
#12150000
b111101 5
1)
#12200000
0)
#12250000
b111100 5
1)
#12300000
0)
#12350000
b111011 5
1)
#12400000
0)
#12450000
b111010 5
1)
#12500000
0)
#12550000
b111001 5
1)
#12600000
0)
#12650000
b111000 5
1)
#12700000
0)
#12750000
b110111 5
1)
#12800000
0)
#12850000
b110110 5
1)
#12900000
0)
#12950000
b110101 5
1)
#13000000
0)
#13050000
b110100 5
1)
#13100000
0)
#13150000
b110011 5
1)
#13200000
0)
#13250000
b110010 5
1)
#13300000
0)
#13350000
b110001 5
1)
#13400000
0)
#13450000
b110000 5
1)
#13500000
0)
#13550000
b101111 5
1)
#13600000
0)
#13650000
b101110 5
1)
#13700000
0)
#13750000
b101101 5
1)
#13800000
0)
#13850000
b101100 5
1)
#13900000
0)
#13950000
b101011 5
1)
#14000000
0)
#14050000
b101010 5
1)
#14100000
0)
#14150000
b101001 5
1)
#14200000
0)
#14250000
b101000 5
1)
#14300000
0)
#14350000
b100111 5
1)
#14400000
0)
#14450000
b100110 5
1)
#14500000
0)
#14550000
b100101 5
1)
#14600000
0)
#14650000
b100100 5
1)
#14700000
0)
#14750000
b100011 5
1)
#14800000
0)
#14850000
b100010 5
1)
#14900000
0)
#14950000
b100001 5
1)
#15000000
0)
#15050000
b100000 5
1)
#15100000
0)
#15150000
b11111 5
1)
#15200000
0)
#15250000
b11110 5
1)
#15300000
0)
#15350000
b11101 5
1)
#15400000
0)
#15450000
b11100 5
1)
#15500000
0)
#15550000
b11011 5
1)
#15600000
0)
#15650000
b11010 5
1)
#15700000
0)
#15750000
b11001 5
1)
#15800000
0)
#15850000
b11000 5
1)
#15900000
0)
#15950000
b10111 5
1)
#16000000
0)
#16050000
b10110 5
1)
#16100000
0)
#16150000
b10101 5
1)
#16200000
0)
#16250000
b10100 5
1)
#16300000
0)
#16350000
b10011 5
1)
#16400000
0)
#16450000
b10010 5
1)
#16500000
0)
#16550000
b10001 5
1)
#16600000
0)
#16650000
b10000 5
1)
#16700000
0)
#16750000
b1111 5
1)
#16800000
0)
#16850000
b1110 5
1)
#16900000
0)
#16950000
b1101 5
1)
#17000000
0)
#17050000
b1100 5
1)
#17100000
0)
#17150000
b1011 5
1)
#17200000
0)
#17250000
b1010 5
1)
#17300000
0)
#17350000
b1001 5
1)
#17400000
0)
#17450000
b1000 5
1)
#17500000
0)
#17550000
b111 5
1)
#17600000
0)
#17650000
b110 5
1)
#17700000
0)
#17750000
b101 5
1)
#17800000
0)
#17850000
b100 5
1)
#17900000
0)
#17950000
b11 5
1)
#18000000
0)
#18050000
b10 5
1)
#18100000
0)
#18150000
b1 5
1)
#18200000
0)
#18250000
b0 5
1)
#18300000
0)
#18350000
b10 9
b100111111 5
1)
#18400000
0)
#18450000
b100111110 5
1)
#18500000
0)
#18550000
b100111101 5
1)
#18600000
0)
#18650000
b100111100 5
1)
#18700000
0)
#18750000
b100111011 5
1)
#18800000
0)
#18850000
b100111010 5
1)
#18900000
0)
#18950000
b100111001 5
1)
#19000000
0)
#19050000
b100111000 5
1)
#19100000
0)
#19150000
b100110111 5
1)
#19200000
0)
#19250000
b100110110 5
1)
#19300000
0)
#19350000
b100110101 5
1)
#19400000
0)
#19450000
b100110100 5
1)
#19500000
0)
#19550000
b100110011 5
1)
#19600000
0)
#19650000
b100110010 5
1)
#19700000
0)
#19750000
b100110001 5
1)
#19800000
0)
#19850000
b100110000 5
1)
#19900000
0)
#19950000
b100101111 5
1)
#20000000
0)
#20050000
b100101110 5
1)
#20100000
0)
#20150000
b100101101 5
1)
#20200000
0)
#20250000
b100101100 5
1)
#20300000
0)
#20350000
b100101011 5
1)
#20400000
0)
#20450000
b100101010 5
1)
#20500000
0)
#20550000
b100101001 5
1)
#20600000
0)
#20650000
b100101000 5
1)
#20700000
0)
#20750000
b100100111 5
1)
#20800000
0)
#20850000
b100100110 5
1)
#20900000
0)
#20950000
b100100101 5
1)
#21000000
0)
#21050000
b100100100 5
1)
#21100000
0)
#21150000
b100100011 5
1)
#21200000
0)
#21250000
b100100010 5
1)
#21300000
0)
#21350000
b100100001 5
1)
#21400000
0)
#21450000
b100100000 5
1)
#21500000
0)
#21550000
b100011111 5
1)
#21600000
0)
#21650000
b100011110 5
1)
#21700000
0)
#21750000
b100011101 5
1)
#21800000
0)
#21850000
b100011100 5
1)
#21900000
0)
#21950000
b100011011 5
1)
#22000000
0)
#22050000
b100011010 5
1)
#22100000
0)
#22150000
b100011001 5
1)
#22200000
0)
#22250000
b100011000 5
1)
#22300000
0)
#22350000
b100010111 5
1)
#22400000
0)
#22450000
b100010110 5
1)
#22500000
0)
#22550000
b100010101 5
1)
#22600000
0)
#22650000
b100010100 5
1)
#22700000
0)
#22750000
b100010011 5
1)
#22800000
0)
#22850000
b100010010 5
1)
#22900000
0)
#22950000
b100010001 5
1)
#23000000
0)
#23050000
b100010000 5
1)
#23100000
0)
#23150000
b100001111 5
1)
#23200000
0)
#23250000
b100001110 5
1)
#23300000
0)
#23350000
b100001101 5
1)
#23400000
0)
#23450000
b100001100 5
1)
#23500000
0)
#23550000
b100001011 5
1)
#23600000
0)
#23650000
b100001010 5
1)
#23700000
0)
#23750000
b100001001 5
1)
#23800000
0)
#23850000
b100001000 5
1)
#23900000
0)
#23950000
b100000111 5
1)
#24000000
0)
#24050000
b100000110 5
1)
#24100000
0)
#24150000
b100000101 5
1)
#24200000
0)
#24250000
b100000100 5
1)
#24300000
0)
#24350000
b100000011 5
1)
#24400000
0)
#24450000
b100000010 5
1)
#24500000
0)
#24550000
b100000001 5
1)
#24600000
0)
#24650000
b100000000 5
1)
#24700000
0)
#24750000
b11111111 5
1)
#24800000
0)
#24850000
b11111110 5
1)
#24900000
0)
#24950000
b11111101 5
1)
#25000000
0)
#25050000
b11111100 5
1)
#25100000
0)
#25150000
b11111011 5
1)
#25200000
0)
#25250000
b11111010 5
1)
#25300000
0)
#25350000
b11111001 5
1)
#25400000
0)
#25450000
b11111000 5
1)
#25500000
0)
#25550000
b11110111 5
1)
#25600000
0)
#25650000
b11110110 5
1)
#25700000
0)
#25750000
b11110101 5
1)
#25800000
0)
#25850000
b11110100 5
1)
#25900000
0)
#25950000
b11110011 5
1)
#26000000
0)
#26050000
b11110010 5
1)
#26100000
0)
#26150000
b11110001 5
1)
#26200000
0)
#26250000
b11110000 5
1)
#26300000
0)
#26350000
b11101111 5
1)
#26400000
0)
#26450000
b11101110 5
1)
#26500000
0)
#26550000
b11101101 5
1)
#26600000
0)
#26650000
b11101100 5
1)
#26700000
0)
#26750000
b11101011 5
1)
#26800000
0)
#26850000
b11101010 5
1)
#26900000
0)
#26950000
b11101001 5
1)
#27000000
0)
#27050000
b11101000 5
1)
#27100000
0)
#27150000
b11100111 5
1)
#27200000
0)
#27250000
b11100110 5
1)
#27300000
0)
#27350000
b11100101 5
1)
#27400000
0)
#27450000
b11100100 5
1)
#27500000
0)
#27550000
b11100011 5
1)
#27600000
0)
#27650000
b11100010 5
1)
#27700000
0)
#27750000
b11100001 5
1)
#27800000
0)
#27850000
b11100000 5
1)
#27900000
0)
#27950000
b11011111 5
1)
#28000000
0)
#28050000
b11011110 5
1)
#28100000
0)
#28150000
b11011101 5
1)
#28200000
0)
#28250000
b11011100 5
1)
#28300000
0)
#28350000
b11011011 5
1)
#28400000
0)
#28450000
b11011010 5
1)
#28500000
0)
#28550000
b11011001 5
1)
#28600000
0)
#28650000
b11011000 5
1)
#28700000
0)
#28750000
b11010111 5
1)
#28800000
0)
#28850000
b11010110 5
1)
#28900000
0)
#28950000
b11010101 5
1)
#29000000
0)
#29050000
b11010100 5
1)
#29100000
0)
#29150000
b11010011 5
1)
#29200000
0)
#29250000
b11010010 5
1)
#29300000
0)
#29350000
b11010001 5
1)
#29400000
0)
#29450000
b11010000 5
1)
#29500000
0)
#29550000
b11001111 5
1)
#29600000
0)
#29650000
b11001110 5
1)
#29700000
0)
#29750000
b11001101 5
1)
#29800000
0)
#29850000
b11001100 5
1)
#29900000
0)
#29950000
b11001011 5
1)
#30000000
0)
#30050000
b11001010 5
1)
#30100000
0)
#30150000
b11001001 5
1)
#30200000
0)
#30250000
b11001000 5
1)
#30300000
0)
#30350000
b11000111 5
1)
#30400000
0)
#30450000
b11000110 5
1)
#30500000
0)
#30550000
b11000101 5
1)
#30600000
0)
#30650000
b11000100 5
1)
#30700000
0)
#30750000
b11000011 5
1)
#30800000
0)
#30850000
b11000010 5
1)
#30900000
0)
#30950000
b11000001 5
1)
#31000000
0)
#31050000
b11000000 5
1)
#31100000
0)
#31150000
b10111111 5
1)
#31200000
0)
#31250000
b10111110 5
1)
#31300000
0)
#31350000
b10111101 5
1)
#31400000
0)
#31450000
b10111100 5
1)
#31500000
0)
#31550000
b10111011 5
1)
#31600000
0)
#31650000
b10111010 5
1)
#31700000
0)
#31750000
b10111001 5
1)
#31800000
0)
#31850000
b10111000 5
1)
#31900000
0)
#31950000
b10110111 5
1)
#32000000
0)
#32050000
b10110110 5
1)
#32100000
0)
#32150000
b10110101 5
1)
#32200000
0)
#32250000
b10110100 5
1)
#32300000
0)
#32350000
b10110011 5
1)
#32400000
0)
#32450000
b10110010 5
1)
#32500000
0)
#32550000
b10110001 5
1)
#32600000
0)
#32650000
b10110000 5
1)
#32700000
0)
#32750000
b10101111 5
1)
#32800000
0)
#32850000
b10101110 5
1)
#32900000
0)
#32950000
b10101101 5
1)
#33000000
0)
#33050000
b10101100 5
1)
#33100000
0)
#33150000
b10101011 5
1)
#33200000
0)
#33250000
b10101010 5
1)
#33300000
0)
#33350000
b10101001 5
1)
#33400000
0)
#33450000
b10101000 5
1)
#33500000
0)
#33550000
b10100111 5
1)
#33600000
0)
#33650000
b10100110 5
1)
#33700000
0)
#33750000
b10100101 5
1)
#33800000
0)
#33850000
b10100100 5
1)
#33900000
0)
#33950000
b10100011 5
1)
#34000000
0)
b0 ;
#34050000
b10100010 5
1)
#34100000
0)
#34150000
b10100001 5
1)
#34200000
0)
#34250000
b10100000 5
1)
#34300000
0)
#34350000
b10011111 5
1)
#34400000
0)
#34450000
b10011110 5
1)
#34500000
0)
#34550000
b10011101 5
1)
#34600000
0)
#34650000
b10011100 5
1)
#34700000
0)
#34750000
b10011011 5
1)
#34800000
0)
#34850000
b10011010 5
1)
#34900000
0)
#34950000
b10011001 5
1)
#35000000
0)
#35050000
b10011000 5
1)
#35100000
0)
#35150000
b10010111 5
1)
#35200000
0)
#35250000
b10010110 5
1)
#35300000
0)
#35350000
b10010101 5
1)
#35400000
0)
#35450000
b10010100 5
1)
#35500000
0)
#35550000
b10010011 5
1)
#35600000
0)
#35650000
b10010010 5
1)
#35700000
0)
#35750000
b10010001 5
1)
#35800000
0)
#35850000
b10010000 5
1)
#35900000
0)
#35950000
b10001111 5
1)
#36000000
0)
#36050000
b10001110 5
1)
#36100000
0)
#36150000
b10001101 5
1)
#36200000
0)
#36250000
b10001100 5
1)
#36300000
0)
#36350000
b10001011 5
1)
#36400000
0)
#36450000
b10001010 5
1)
#36500000
0)
#36550000
b10001001 5
1)
#36600000
0)
#36650000
b10001000 5
1)
#36700000
0)
#36750000
b10000111 5
1)
#36800000
0)
#36850000
b10000110 5
1)
#36900000
0)
#36950000
b10000101 5
1)
#37000000
0)
#37050000
b10000100 5
1)
#37100000
0)
#37150000
b10000011 5
1)
#37200000
0)
#37250000
b10000010 5
1)
#37300000
0)
#37350000
b10000001 5
1)
#37400000
0)
#37450000
b10000000 5
1)
#37500000
0)
#37550000
b1111111 5
1)
#37600000
0)
#37650000
b1111110 5
1)
#37700000
0)
#37750000
b1111101 5
1)
#37800000
0)
#37850000
b1111100 5
1)
#37900000
0)
#37950000
b1111011 5
1)
#38000000
0)
#38050000
b1111010 5
1)
#38100000
0)
#38150000
b1111001 5
1)
#38200000
0)
#38250000
b1111000 5
1)
#38300000
0)
#38350000
b1110111 5
1)
#38400000
0)
#38450000
b1110110 5
1)
#38500000
0)
#38550000
b1110101 5
1)
#38600000
0)
#38650000
b1110100 5
1)
#38700000
0)
#38750000
b1110011 5
1)
#38800000
0)
#38850000
b1110010 5
1)
#38900000
0)
#38950000
b1110001 5
1)
#39000000
0)
#39050000
b1110000 5
1)
#39100000
0)
#39150000
b1101111 5
1)
#39200000
0)
#39250000
b1101110 5
1)
#39300000
0)
#39350000
b1101101 5
1)
#39400000
0)
#39450000
b1101100 5
1)
#39500000
0)
#39550000
b1101011 5
1)
#39600000
0)
#39650000
b1101010 5
1)
#39700000
0)
#39750000
b1101001 5
1)
#39800000
0)
#39850000
b1101000 5
1)
#39900000
0)
#39950000
b1100111 5
1)
#40000000
0)
#40050000
b1100110 5
1)
#40100000
0)
#40150000
b1100101 5
1)
#40200000
0)
#40250000
b1100100 5
1)
#40300000
0)
#40350000
b1100011 5
1)
#40400000
0)
#40450000
b1100010 5
1)
#40500000
0)
#40550000
b1100001 5
1)
#40600000
0)
#40650000
b1100000 5
1)
#40700000
0)
#40750000
b1011111 5
1)
#40800000
0)
#40850000
b1011110 5
1)
#40900000
0)
#40950000
b1011101 5
1)
#41000000
0)
#41050000
b1011100 5
1)
#41100000
0)
#41150000
b1011011 5
1)
#41200000
0)
#41250000
b1011010 5
1)
#41300000
0)
#41350000
b1011001 5
1)
#41400000
0)
#41450000
b1011000 5
1)
#41500000
0)
#41550000
b1010111 5
1)
#41600000
0)
#41650000
b1010110 5
1)
#41700000
0)
#41750000
b1010101 5
1)
#41800000
0)
#41850000
b1010100 5
1)
#41900000
0)
#41950000
b1010011 5
1)
#42000000
0)
#42050000
b1010010 5
1)
#42100000
0)
#42150000
b1010001 5
1)
#42200000
0)
#42250000
b1010000 5
1)
#42300000
0)
#42350000
b1001111 5
1)
#42400000
0)
#42450000
b1001110 5
1)
#42500000
0)
#42550000
b1001101 5
1)
#42600000
0)
#42650000
b1001100 5
1)
#42700000
0)
#42750000
b1001011 5
1)
#42800000
0)
#42850000
b1001010 5
1)
#42900000
0)
#42950000
b1001001 5
1)
#43000000
0)
#43050000
b1001000 5
1)
#43100000
0)
#43150000
b1000111 5
1)
#43200000
0)
#43250000
b1000110 5
1)
#43300000
0)
#43350000
b1000101 5
1)
#43400000
0)
#43450000
b1000100 5
1)
#43500000
0)
#43550000
b1000011 5
1)
#43600000
0)
#43650000
b1000010 5
1)
#43700000
0)
#43750000
b1000001 5
1)
#43800000
0)
#43850000
b1000000 5
1)
#43900000
0)
#43950000
b111111 5
1)
#44000000
0)
#44050000
b111110 5
1)
#44100000
0)
#44150000
b111101 5
1)
#44200000
0)
#44250000
b111100 5
1)
#44300000
0)
#44350000
b111011 5
1)
#44400000
0)
#44450000
b111010 5
1)
#44500000
0)
#44550000
b111001 5
1)
#44600000
0)
#44650000
b111000 5
1)
#44700000
0)
#44750000
b110111 5
1)
#44800000
0)
#44850000
b110110 5
1)
#44900000
0)
#44950000
b110101 5
1)
#45000000
0)
#45050000
b110100 5
1)
#45100000
0)
#45150000
b110011 5
1)
#45200000
0)
#45250000
b110010 5
1)
#45300000
0)
#45350000
b110001 5
1)
#45400000
0)
#45450000
b110000 5
1)
#45500000
0)
#45550000
b101111 5
1)
#45600000
0)
#45650000
b101110 5
1)
#45700000
0)
#45750000
b101101 5
1)
#45800000
0)
#45850000
b101100 5
1)
#45900000
0)
#45950000
b101011 5
1)
#46000000
0)
#46050000
b101010 5
1)
#46100000
0)
#46150000
b101001 5
1)
#46200000
0)
#46250000
b101000 5
1)
#46300000
0)
#46350000
b100111 5
1)
#46400000
0)
#46450000
b100110 5
1)
#46500000
0)
#46550000
b100101 5
1)
#46600000
0)
#46650000
b100100 5
1)
#46700000
0)
#46750000
b100011 5
1)
#46800000
0)
#46850000
b100010 5
1)
#46900000
0)
#46950000
b100001 5
1)
#47000000
0)
#47050000
b100000 5
1)
#47100000
0)
#47150000
b11111 5
1)
#47200000
0)
#47250000
b11110 5
1)
#47300000
0)
#47350000
b11101 5
1)
#47400000
0)
#47450000
b11100 5
1)
#47500000
0)
#47550000
b11011 5
1)
#47600000
0)
#47650000
b11010 5
1)
#47700000
0)
#47750000
b11001 5
1)
#47800000
0)
#47850000
b11000 5
1)
#47900000
0)
#47950000
b10111 5
1)
#48000000
0)
#48050000
b10110 5
1)
#48100000
0)
#48150000
b10101 5
1)
#48200000
0)
#48250000
b10100 5
1)
#48300000
0)
#48350000
b10011 5
1)
#48400000
0)
#48450000
b10010 5
1)
#48500000
0)
#48550000
b10001 5
1)
#48600000
0)
#48650000
b10000 5
1)
#48700000
0)
#48750000
b1111 5
1)
#48800000
0)
#48850000
b1110 5
1)
#48900000
0)
#48950000
b1101 5
1)
#49000000
0)
#49050000
b1100 5
1)
#49100000
0)
#49150000
b1011 5
1)
#49200000
0)
#49250000
b1010 5
1)
#49300000
0)
#49350000
b1001 5
1)
#49400000
0)
#49450000
b1000 5
1)
