devEnv/sim/src/sinSrc.v
module sine_wave_ob #(
    parameter TABLE_BITS = 6,   // 2^6 = 64 samples
    parameter AMP_BITS   = 8    // 8 bits (0..255)
)(
    input  wire                   clk,
    input  wire                   rst,        // active high
    input  wire [TABLE_BITS-1:0]  step,       // NCO frequency control
    output reg  [AMP_BITS-1:0]    sine_out,   // offset-binary: 0..255
    output wire signed [23:0]     pcm_sample  // signed PCM -32768..+32767 (24b)
);
    localparam integer TABLE_SIZE = (1 << TABLE_BITS);

    // ROM: 64 samples, center 128 (offset-binary)
    reg [AMP_BITS-1:0] rom [0:TABLE_SIZE-1];

    // Phase accumulator (6 bits): index = phase
    reg [TABLE_BITS-1:0] index;

    integer i;
    real ang;
    initial begin
        // generate sine lookup table (simulation only)
        for (i = 0; i < TABLE_SIZE; i = i + 1) begin
            ang = 2.0 * 3.141592653589793 * i / TABLE_SIZE;
            // offset-binary: center 128, amplitude 127
            rom[i] = $rtoi(128.0 + 127.0 * $sin(ang));
        end
    end

    // NCO phase accumulator
    always @(posedge clk or posedge rst) begin
        if (rst)
            index <= {TABLE_BITS{1'b0}};
        else
            index <= index + step;
    end

    // Output register
    always @(posedge clk or posedge rst) begin
        if (rst)
            sine_out <= 8'd128;
        else
            sine_out <= rom[index];
    end

    // ---- PCM pipeline: convert offset-binary -> signed 24-bit ----
    // 0..255 -> -32768..+32767 -> 24-bit signed
    assign pcm_sample = { {16{sine_out[7]}}, sine_out } - 24'd32768;

endmodule

devEnv/sim/tb/sinTB.v
`timescale 1ns/1ps
module tb_sine_wave_ob;
    reg clk, rst;
    reg  [5:0] step;
    wire [7:0] sine_out;
    wire signed [23:0] pcm_sample;

    // DUT
    sine_wave_ob #(.TABLE_BITS(6), .AMP_BITS(8)) dut (
        .clk(clk),
        .rst(rst),
        .step(step),
        .sine_out(sine_out),
        .pcm_sample(pcm_sample)
    );

    // 50 MHz
    initial begin clk = 0; forever #10 clk = ~clk; end

    initial begin
        $dumpfile("sine_wave.vcd");
        $dumpvars(0, tb_sine_wave_ob);

        // reset
        rst = 1; step = 6'd0;
        #100; rst = 0;

        // test several frequencies
        step = 6'd1;   #4000;
        step = 6'd2;   #4000;
        step = 6'd4;   #4000;
        step = 6'd8;   #4000;

        $finish;
    end

    initial begin
        $display("t(ns)\tstep\tindex\tsine_out\tpcm_sample");
        $monitor("%0t\t%0d\t%0d\t%0d\t%d", 
                 $time, step, dut.index, sine_out, pcm_sample);
    end
endmodule

devEnv/sim/sine_wave.vcd
$date
	Mon Nov 10 17:19:36 2025
$end
$version
	Icarus Verilog
$end
$timescale
	1ps
$end
$scope module tb_sine_wave_ob $end
$var wire 8 ! sine_out [7:0] $end
$var wire 24 " pcm_sample [23:0] $end
$var reg 1 # clk $end
$var reg 1 $ rst $end
$var reg 6 % step [5:0] $end
$scope module dut $end
$var wire 1 # clk $end
$var wire 1 $ rst $end
$var wire 6 & step [5:0] $end
$var wire 24 ' pcm_sample [23:0] $end
$var parameter 32 ( AMP_BITS $end
$var parameter 32 ) TABLE_BITS $end
$var parameter 32 * TABLE_SIZE $end
$var reg 6 + index [5:0] $end
$var reg 8 , sine_out [7:0] $end
$var real 1 - ang $end
$var integer 32 . i [31:0] $end
$upscope $end
$upscope $end
$enddefinitions $end
$comment Show the parameter values. $end
$dumpall
b1000000 *
b110 )
b1000 (
$end
#0
$dumpvars
b1000000 .
r6.185010536754906 -
b10000000 ,
b0 +
b111111110111111110000000 '
b0 &
b0 %
1$
0#
b111111110111111110000000 "
b10000000 !
$end
#10000
1#
#20000
0#
#30000
1#
#40000
0#
#50000
1#
#60000
0#
#70000
1#
#80000
0#
#90000
1#
#100000
0#
b1 %
b1 &
0$
#110000
b1 +
1#
#120000
0#
#130000
b111111110111111110001100 "
b111111110111111110001100 '
b10001100 !
b10001100 ,
b10 +
1#
#140000
0#
#150000
b11 +
b111111110111111110011000 "
b111111110111111110011000 '
b10011000 !
b10011000 ,
1#
#160000
0#
#170000
b111111110111111110100100 "
b111111110111111110100100 '
b10100100 !
b10100100 ,
b100 +
1#
#180000
0#
#190000
b101 +
b111111110111111110110000 "
b111111110111111110110000 '
b10110000 !
b10110000 ,
1#
#200000
0#
#210000
b111111110111111110111011 "
b111111110111111110111011 '
b10111011 !
b10111011 ,
b110 +
1#
#220000
0#
#230000
b111 +
b111111110111111111000110 "
b111111110111111111000110 '
b11000110 !
b11000110 ,
1#
#240000
0#
#250000
b111111110111111111010000 "
b111111110111111111010000 '
b11010000 !
b11010000 ,
b1000 +
1#
#260000
0#
#270000
b1001 +
b111111110111111111011001 "
b111111110111111111011001 '
b11011001 !
b11011001 ,
1#
#280000
0#
#290000
b111111110111111111100010 "
b111111110111111111100010 '
b11100010 !
b11100010 ,
b1010 +
1#
#300000
0#
#310000
b1011 +
b111111110111111111101001 "
b111111110111111111101001 '
b11101001 !
b11101001 ,
1#
#320000
0#
#330000
b111111110111111111110000 "
b111111110111111111110000 '
b11110000 !
b11110000 ,
b1100 +
1#
#340000
0#
#350000
b1101 +
b111111110111111111110101 "
b111111110111111111110101 '
b11110101 !
b11110101 ,
1#
#360000
0#
#370000
b111111110111111111111001 "
b111111110111111111111001 '
b11111001 !
b11111001 ,
b1110 +
1#
#380000
0#
#390000
b1111 +
b111111110111111111111100 "
b111111110111111111111100 '
b11111100 !
b11111100 ,
1#
#400000
0#
#410000
b111111110111111111111110 "
b111111110111111111111110 '
b11111110 !
b11111110 ,
b10000 +
1#
#420000
0#
#430000
b10001 +
b111111110111111111111111 "
b111111110111111111111111 '
b11111111 !
b11111111 ,
1#
#440000
0#
#450000
b111111110111111111111110 "
b111111110111111111111110 '
b11111110 !
b11111110 ,
b10010 +
1#
#460000
0#
#470000
b10011 +
b111111110111111111111100 "
b111111110111111111111100 '
b11111100 !
b11111100 ,
1#
#480000
0#
#490000
b111111110111111111111001 "
b111111110111111111111001 '
b11111001 !
b11111001 ,
b10100 +
1#
#500000
0#
#510000
b10101 +
b111111110111111111110101 "
b111111110111111111110101 '
b11110101 !
b11110101 ,
1#
#520000
0#
#530000
b111111110111111111110000 "
b111111110111111111110000 '
b11110000 !
b11110000 ,
b10110 +
1#
#540000
0#
#550000
b10111 +
b111111110111111111101001 "
b111111110111111111101001 '
b11101001 !
b11101001 ,
1#
#560000
0#
#570000
b111111110111111111100010 "
b111111110111111111100010 '
b11100010 !
b11100010 ,
b11000 +
1#
#580000
0#
#590000
b11001 +
b111111110111111111011001 "
b111111110111111111011001 '
b11011001 !
b11011001 ,
1#
#600000
0#
#610000
b111111110111111111010000 "
b111111110111111111010000 '
b11010000 !
b11010000 ,
b11010 +
1#
#620000
0#
#630000
b11011 +
b111111110111111111000110 "
b111111110111111111000110 '
b11000110 !
b11000110 ,
1#
#640000
0#
#650000
b111111110111111110111011 "
b111111110111111110111011 '
b10111011 !
b10111011 ,
b11100 +
1#
#660000
0#
#670000
b11101 +
b111111110111111110110000 "
b111111110111111110110000 '
b10110000 !
b10110000 ,
1#
#680000
0#
#690000
b111111110111111110100100 "
b111111110111111110100100 '
b10100100 !
b10100100 ,
b11110 +
1#
#700000
0#
#710000
b11111 +
b111111110111111110011000 "
b111111110111111110011000 '
b10011000 !
b10011000 ,
1#
#720000
0#
#730000
b111111110111111110001100 "
b111111110111111110001100 '
b10001100 !
b10001100 ,
b100000 +
1#
#740000
0#
#750000
b100001 +
b111111110111111110000000 "
b111111110111111110000000 '
b10000000 !
b10000000 ,
1#
#760000
0#
#770000
b111111111000000001110011 "
b111111111000000001110011 '
b1110011 !
b1110011 ,
b100010 +
1#
#780000
0#
#790000
b100011 +
b111111111000000001100111 "
b111111111000000001100111 '
b1100111 !
b1100111 ,
1#
#800000
0#
#810000
b111111111000000001011011 "
b111111111000000001011011 '
b1011011 !
b1011011 ,
b100100 +
1#
#820000
0#
#830000
b100101 +
b111111111000000001001111 "
b111111111000000001001111 '
b1001111 !
b1001111 ,
1#
#840000
0#
#850000
b111111111000000001000100 "
b111111111000000001000100 '
b1000100 !
b1000100 ,
b100110 +
1#
#860000
0#
#870000
b100111 +
b111111111000000000111001 "
b111111111000000000111001 '
b111001 !
b111001 ,
1#
#880000
0#
#890000
b111111111000000000101111 "
b111111111000000000101111 '
b101111 !
b101111 ,
b101000 +
1#
#900000
0#
#910000
b101001 +
b111111111000000000100110 "
b111111111000000000100110 '
b100110 !
b100110 ,
1#
#920000
0#
#930000
b111111111000000000011101 "
b111111111000000000011101 '
b11101 !
b11101 ,
b101010 +
1#
#940000
0#
#950000
b101011 +
b111111111000000000010110 "
b111111111000000000010110 '
b10110 !
b10110 ,
1#
#960000
0#
#970000
b111111111000000000001111 "
b111111111000000000001111 '
b1111 !
b1111 ,
b101100 +
1#
#980000
0#
#990000
b101101 +
b111111111000000000001010 "
b111111111000000000001010 '
b1010 !
b1010 ,
1#
#1000000
0#
#1010000
b111111111000000000000110 "
b111111111000000000000110 '
b110 !
b110 ,
b101110 +
1#
#1020000
0#
#1030000
b101111 +
b111111111000000000000011 "
b111111111000000000000011 '
b11 !
b11 ,
1#
#1040000
0#
#1050000
b111111111000000000000001 "
b111111111000000000000001 '
b1 !
b1 ,
b110000 +
1#
#1060000
0#
#1070000
b110001 +
1#
#1080000
0#
#1090000
b110010 +
1#
#1100000
0#
#1110000
b110011 +
b111111111000000000000011 "
b111111111000000000000011 '
b11 !
b11 ,
1#
#1120000
0#
#1130000
b111111111000000000000110 "
b111111111000000000000110 '
b110 !
b110 ,
b110100 +
1#
#1140000
0#
#1150000
b110101 +
b111111111000000000001010 "
b111111111000000000001010 '
b1010 !
b1010 ,
1#
#1160000
0#
#1170000
b111111111000000000001111 "
b111111111000000000001111 '
b1111 !
b1111 ,
b110110 +
1#
#1180000
0#
#1190000
b110111 +
b111111111000000000010110 "
b111111111000000000010110 '
b10110 !
b10110 ,
1#
#1200000
0#
#1210000
b111111111000000000011101 "
b111111111000000000011101 '
b11101 !
b11101 ,
b111000 +
1#
#1220000
0#
#1230000
b111001 +
b111111111000000000100110 "
b111111111000000000100110 '
b100110 !
b100110 ,
1#
#1240000
0#
#1250000
b111111111000000000101111 "
b111111111000000000101111 '
b101111 !
b101111 ,
b111010 +
1#
#1260000
0#
#1270000
b111011 +
b111111111000000000111001 "
b111111111000000000111001 '
b111001 !
b111001 ,
1#
#1280000
0#
#1290000
b111111111000000001000100 "
b111111111000000001000100 '
b1000100 !
b1000100 ,
b111100 +
1#
#1300000
0#
#1310000
b111101 +
b111111111000000001001111 "
b111111111000000001001111 '
b1001111 !
b1001111 ,
1#
#1320000
0#
#1330000
b111111111000000001011011 "
b111111111000000001011011 '
b1011011 !
b1011011 ,
b111110 +
1#
#1340000
0#
#1350000
b111111 +
b111111111000000001100111 "
b111111111000000001100111 '
b1100111 !
b1100111 ,
1#
#1360000
0#
#1370000
b111111111000000001110011 "
b111111111000000001110011 '
b1110011 !
b1110011 ,
b0 +
1#
#1380000
0#
#1390000
b1 +
b111111110111111110000000 "
b111111110111111110000000 '
b10000000 !
b10000000 ,
1#
#1400000
0#
#1410000
b111111110111111110001100 "
b111111110111111110001100 '
b10001100 !
b10001100 ,
b10 +
1#
#1420000
0#
#1430000
b11 +
b111111110111111110011000 "
b111111110111111110011000 '
b10011000 !
b10011000 ,
1#
#1440000
0#
#1450000
b111111110111111110100100 "
b111111110111111110100100 '
b10100100 !
b10100100 ,
b100 +
1#
#1460000
0#
#1470000
b101 +
b111111110111111110110000 "
b111111110111111110110000 '
b10110000 !
b10110000 ,
1#
#1480000
0#
#1490000
b111111110111111110111011 "
b111111110111111110111011 '
b10111011 !
b10111011 ,
b110 +
1#
#1500000
0#
#1510000
b111 +
b111111110111111111000110 "
b111111110111111111000110 '
b11000110 !
b11000110 ,
1#
#1520000
0#
#1530000
b111111110111111111010000 "
b111111110111111111010000 '
b11010000 !
b11010000 ,
b1000 +
1#
#1540000
0#
#1550000
b1001 +
b111111110111111111011001 "
b111111110111111111011001 '
b11011001 !
b11011001 ,
1#
#1560000
0#
#1570000
b111111110111111111100010 "
b111111110111111111100010 '
b11100010 !
b11100010 ,
b1010 +
1#
#1580000
0#
#1590000
b1011 +
b111111110111111111101001 "
b111111110111111111101001 '
b11101001 !
b11101001 ,
1#
#1600000
0#
#1610000
b111111110111111111110000 "
b111111110111111111110000 '
b11110000 !
b11110000 ,
b1100 +
1#
#1620000
0#
#1630000
b1101 +
b111111110111111111110101 "
b111111110111111111110101 '
b11110101 !
b11110101 ,
1#
#1640000
0#
#1650000
b111111110111111111111001 "
b111111110111111111111001 '
b11111001 !
b11111001 ,
b1110 +
1#
#1660000
0#
#1670000
b1111 +
b111111110111111111111100 "
b111111110111111111111100 '
b11111100 !
b11111100 ,
1#
#1680000
0#
#1690000
b111111110111111111111110 "
b111111110111111111111110 '
b11111110 !
b11111110 ,
b10000 +
1#
#1700000
0#
#1710000
b10001 +
b111111110111111111111111 "
b111111110111111111111111 '
b11111111 !
b11111111 ,
1#
#1720000
0#
#1730000
b111111110111111111111110 "
b111111110111111111111110 '
b11111110 !
b11111110 ,
b10010 +
1#
#1740000
0#
#1750000
b10011 +
b111111110111111111111100 "
b111111110111111111111100 '
b11111100 !
b11111100 ,
1#
#1760000
0#
#1770000
b111111110111111111111001 "
b111111110111111111111001 '
b11111001 !
b11111001 ,
b10100 +
1#
#1780000
0#
#1790000
b10101 +
b111111110111111111110101 "
b111111110111111111110101 '
b11110101 !
b11110101 ,
1#
#1800000
0#
#1810000
b111111110111111111110000 "
b111111110111111111110000 '
b11110000 !
b11110000 ,
b10110 +
1#
#1820000
0#
#1830000
b10111 +
b111111110111111111101001 "
b111111110111111111101001 '
b11101001 !
b11101001 ,
1#
#1840000
0#
#1850000
b111111110111111111100010 "
b111111110111111111100010 '
b11100010 !
b11100010 ,
b11000 +
1#
#1860000
0#
#1870000
b11001 +
b111111110111111111011001 "
b111111110111111111011001 '
b11011001 !
b11011001 ,
1#
#1880000
0#
#1890000
b111111110111111111010000 "
b111111110111111111010000 '
b11010000 !
b11010000 ,
b11010 +
1#
#1900000
0#
#1910000
b11011 +
b111111110111111111000110 "
b111111110111111111000110 '
b11000110 !
b11000110 ,
1#
#1920000
0#
#1930000
b111111110111111110111011 "
b111111110111111110111011 '
b10111011 !
b10111011 ,
b11100 +
1#
#1940000
0#
#1950000
b11101 +
b111111110111111110110000 "
b111111110111111110110000 '
b10110000 !
b10110000 ,
1#
#1960000
0#
#1970000
b111111110111111110100100 "
b111111110111111110100100 '
b10100100 !
b10100100 ,
b11110 +
1#
#1980000
0#
#1990000
b11111 +
b111111110111111110011000 "
b111111110111111110011000 '
b10011000 !
b10011000 ,
1#
#2000000
0#
#2010000
b111111110111111110001100 "
b111111110111111110001100 '
b10001100 !
b10001100 ,
b100000 +
1#
#2020000
0#
#2030000
b100001 +
b111111110111111110000000 "
b111111110111111110000000 '
b10000000 !
b10000000 ,
1#
#2040000
0#
#2050000
b111111111000000001110011 "
b111111111000000001110011 '
b1110011 !
b1110011 ,
b100010 +
1#
#2060000
0#
#2070000
b100011 +
b111111111000000001100111 "
b111111111000000001100111 '
b1100111 !
b1100111 ,
1#
#2080000
0#
#2090000
b111111111000000001011011 "
b111111111000000001011011 '
b1011011 !
b1011011 ,
b100100 +
1#
#2100000
0#
#2110000
b100101 +
b111111111000000001001111 "
b111111111000000001001111 '
b1001111 !
b1001111 ,
1#
#2120000
0#
#2130000
b111111111000000001000100 "
b111111111000000001000100 '
b1000100 !
b1000100 ,
b100110 +
1#
#2140000
0#
#2150000
b100111 +
b111111111000000000111001 "
b111111111000000000111001 '
b111001 !
b111001 ,
1#
#2160000
0#
#2170000
b111111111000000000101111 "
b111111111000000000101111 '
b101111 !
b101111 ,
b101000 +
1#
#2180000
0#
#2190000
b101001 +
b111111111000000000100110 "
b111111111000000000100110 '
b100110 !
b100110 ,
1#
#2200000
0#
#2210000
b111111111000000000011101 "
b111111111000000000011101 '
b11101 !
b11101 ,
b101010 +
1#
#2220000
0#
#2230000
b101011 +
b111111111000000000010110 "
b111111111000000000010110 '
b10110 !
b10110 ,
1#
#2240000
0#
#2250000
b111111111000000000001111 "
b111111111000000000001111 '
b1111 !
b1111 ,
b101100 +
1#
#2260000
0#
#2270000
b101101 +
b111111111000000000001010 "
b111111111000000000001010 '
b1010 !
b1010 ,
1#
#2280000
0#
#2290000
b111111111000000000000110 "
b111111111000000000000110 '
b110 !
b110 ,
b101110 +
1#
#2300000
0#
#2310000
b101111 +
b111111111000000000000011 "
b111111111000000000000011 '
b11 !
b11 ,
1#
#2320000
0#
#2330000
b111111111000000000000001 "
b111111111000000000000001 '
b1 !
b1 ,
b110000 +
1#
#2340000
0#
#2350000
b110001 +
1#
#2360000
0#
#2370000
b110010 +
1#
#2380000
0#
#2390000
b110011 +
b111111111000000000000011 "
b111111111000000000000011 '
b11 !
b11 ,
1#
#2400000
0#
#2410000
b111111111000000000000110 "
b111111111000000000000110 '
b110 !
b110 ,
b110100 +
1#
#2420000
0#
#2430000
b110101 +
b111111111000000000001010 "
b111111111000000000001010 '
b1010 !
b1010 ,
1#
#2440000
0#
#2450000
b111111111000000000001111 "
b111111111000000000001111 '
b1111 !
b1111 ,
b110110 +
1#
#2460000
0#
#2470000
b110111 +
b111111111000000000010110 "
b111111111000000000010110 '
b10110 !
b10110 ,
1#
#2480000
0#
#2490000
b111111111000000000011101 "
b111111111000000000011101 '
b11101 !
b11101 ,
b111000 +
1#
#2500000
0#
#2510000
b111001 +
b111111111000000000100110 "
b111111111000000000100110 '
b100110 !
b100110 ,
1#
#2520000
0#
#2530000
b111111111000000000101111 "
b111111111000000000101111 '
b101111 !
b101111 ,
b111010 +
1#
#2540000
0#
#2550000
b111011 +
b111111111000000000111001 "
b111111111000000000111001 '
b111001 !
b111001 ,
1#
#2560000
0#
#2570000
b111111111000000001000100 "
b111111111000000001000100 '
b1000100 !
b1000100 ,
b111100 +
1#
#2580000
0#
#2590000
b111101 +
b111111111000000001001111 "
b111111111000000001001111 '
b1001111 !
b1001111 ,
1#
#2600000
0#
#2610000
b111111111000000001011011 "
b111111111000000001011011 '
b1011011 !
b1011011 ,
b111110 +
1#
#2620000
0#
#2630000
b111111 +
b111111111000000001100111 "
b111111111000000001100111 '
b1100111 !
b1100111 ,
1#
#2640000
0#
#2650000
b111111111000000001110011 "
b111111111000000001110011 '
b1110011 !
b1110011 ,
b0 +
1#
#2660000
0#
#2670000
b1 +
b111111110111111110000000 "
b111111110111111110000000 '
b10000000 !
b10000000 ,
1#
#2680000
0#
#2690000
b111111110111111110001100 "
b111111110111111110001100 '
b10001100 !
b10001100 ,
b10 +
1#
#2700000
0#
#2710000
b11 +
b111111110111111110011000 "
b111111110111111110011000 '
b10011000 !
b10011000 ,
1#
#2720000
0#
#2730000
b111111110111111110100100 "
b111111110111111110100100 '
b10100100 !
b10100100 ,
b100 +
1#
#2740000
0#
#2750000
b101 +
b111111110111111110110000 "
b111111110111111110110000 '
b10110000 !
b10110000 ,
1#
#2760000
0#
#2770000
b111111110111111110111011 "
b111111110111111110111011 '
b10111011 !
b10111011 ,
b110 +
1#
#2780000
0#
#2790000
b111 +
b111111110111111111000110 "
b111111110111111111000110 '
b11000110 !
b11000110 ,
1#
#2800000
0#
#2810000
b111111110111111111010000 "
b111111110111111111010000 '
b11010000 !
b11010000 ,
b1000 +
1#
#2820000
0#
#2830000
b1001 +
b111111110111111111011001 "
b111111110111111111011001 '
b11011001 !
b11011001 ,
1#
#2840000
0#
#2850000
b111111110111111111100010 "
b111111110111111111100010 '
b11100010 !
b11100010 ,
b1010 +
1#
#2860000
0#
#2870000
b1011 +
b111111110111111111101001 "
b111111110111111111101001 '
b11101001 !
b11101001 ,
1#
#2880000
0#
#2890000
b111111110111111111110000 "
b111111110111111111110000 '
b11110000 !
b11110000 ,
b1100 +
1#
#2900000
0#
#2910000
b1101 +
b111111110111111111110101 "
b111111110111111111110101 '
b11110101 !
b11110101 ,
1#
#2920000
0#
#2930000
b111111110111111111111001 "
b111111110111111111111001 '
b11111001 !
b11111001 ,
b1110 +
1#
#2940000
0#
#2950000
b1111 +
b111111110111111111111100 "
b111111110111111111111100 '
b11111100 !
b11111100 ,
1#
#2960000
0#
#2970000
b111111110111111111111110 "
b111111110111111111111110 '
b11111110 !
b11111110 ,
b10000 +
1#
#2980000
0#
#2990000
b10001 +
b111111110111111111111111 "
b111111110111111111111111 '
b11111111 !
b11111111 ,
1#
#3000000
0#
#3010000
b111111110111111111111110 "
b111111110111111111111110 '
b11111110 !
b11111110 ,
b10010 +
1#
#3020000
0#
#3030000
b10011 +
b111111110111111111111100 "
b111111110111111111111100 '
b11111100 !
b11111100 ,
1#
#3040000
0#
#3050000
b111111110111111111111001 "
b111111110111111111111001 '
b11111001 !
b11111001 ,
b10100 +
1#
#3060000
0#
#3070000
b10101 +
b111111110111111111110101 "
b111111110111111111110101 '
b11110101 !
b11110101 ,
1#
#3080000
0#
#3090000
b111111110111111111110000 "
b111111110111111111110000 '
b11110000 !
b11110000 ,
b10110 +
1#
#3100000
0#
#3110000
b10111 +
b111111110111111111101001 "
b111111110111111111101001 '
b11101001 !
b11101001 ,
1#
#3120000
0#
#3130000
b111111110111111111100010 "
b111111110111111111100010 '
b11100010 !
b11100010 ,
b11000 +
1#
#3140000
0#
#3150000
b11001 +
b111111110111111111011001 "
b111111110111111111011001 '
b11011001 !
b11011001 ,
1#
#3160000
0#
#3170000
b111111110111111111010000 "
b111111110111111111010000 '
b11010000 !
b11010000 ,
b11010 +
1#
#3180000
0#
#3190000
b11011 +
b111111110111111111000110 "
b111111110111111111000110 '
b11000110 !
b11000110 ,
1#
#3200000
0#
#3210000
b111111110111111110111011 "
b111111110111111110111011 '
b10111011 !
b10111011 ,
b11100 +
1#
#3220000
0#
#3230000
b11101 +
b111111110111111110110000 "
b111111110111111110110000 '
b10110000 !
b10110000 ,
1#
#3240000
0#
#3250000
b111111110111111110100100 "
b111111110111111110100100 '
b10100100 !
b10100100 ,
b11110 +
1#
#3260000
0#
#3270000
b11111 +
b111111110111111110011000 "
b111111110111111110011000 '
b10011000 !
b10011000 ,
1#
#3280000
0#
#3290000
b111111110111111110001100 "
b111111110111111110001100 '
b10001100 !
b10001100 ,
b100000 +
1#
#3300000
0#
#3310000
b100001 +
b111111110111111110000000 "
b111111110111111110000000 '
b10000000 !
b10000000 ,
1#
#3320000
0#
#3330000
b111111111000000001110011 "
b111111111000000001110011 '
b1110011 !
b1110011 ,
b100010 +
1#
#3340000
0#
#3350000
b100011 +
b111111111000000001100111 "
b111111111000000001100111 '
b1100111 !
b1100111 ,
1#
#3360000
0#
#3370000
b111111111000000001011011 "
b111111111000000001011011 '
b1011011 !
b1011011 ,
b100100 +
1#
#3380000
0#
#3390000
b100101 +
b111111111000000001001111 "
b111111111000000001001111 '
b1001111 !
b1001111 ,
1#
#3400000
0#
#3410000
b111111111000000001000100 "
b111111111000000001000100 '
b1000100 !
b1000100 ,
b100110 +
1#
#3420000
0#
#3430000
b100111 +
b111111111000000000111001 "
b111111111000000000111001 '
b111001 !
b111001 ,
1#
#3440000
0#
#3450000
b111111111000000000101111 "
b111111111000000000101111 '
b101111 !
b101111 ,
b101000 +
1#
#3460000
0#
#3470000
b101001 +
b111111111000000000100110 "
b111111111000000000100110 '
b100110 !
b100110 ,
1#
#3480000
0#
#3490000
b111111111000000000011101 "
b111111111000000000011101 '
b11101 !
b11101 ,
b101010 +
1#
#3500000
0#
#3510000
b101011 +
b111111111000000000010110 "
b111111111000000000010110 '
b10110 !
b10110 ,
1#
#3520000
0#
#3530000
b111111111000000000001111 "
b111111111000000000001111 '
b1111 !
b1111 ,
b101100 +
1#
#3540000
0#
#3550000
b101101 +
b111111111000000000001010 "
b111111111000000000001010 '
b1010 !
b1010 ,
1#
#3560000
0#
#3570000
b111111111000000000000110 "
b111111111000000000000110 '
b110 !
b110 ,
b101110 +
1#
#3580000
0#
#3590000
b101111 +
b111111111000000000000011 "
b111111111000000000000011 '
b11 !
b11 ,
1#
#3600000
0#
#3610000
b111111111000000000000001 "
b111111111000000000000001 '
b1 !
b1 ,
b110000 +
1#
#3620000
0#
#3630000
b110001 +
1#
#3640000
0#
#3650000
b110010 +
1#
#3660000
0#
#3670000
b110011 +
b111111111000000000000011 "
b111111111000000000000011 '
b11 !
b11 ,
1#
#3680000
0#
#3690000
b111111111000000000000110 "
b111111111000000000000110 '
b110 !
b110 ,
b110100 +
1#
#3700000
0#
#3710000
b110101 +
b111111111000000000001010 "
b111111111000000000001010 '
b1010 !
b1010 ,
1#
#3720000
0#
#3730000
b111111111000000000001111 "
b111111111000000000001111 '
b1111 !
b1111 ,
b110110 +
1#
#3740000
0#
#3750000
b110111 +
b111111111000000000010110 "
b111111111000000000010110 '
b10110 !
b10110 ,
1#
#3760000
0#
#3770000
b111111111000000000011101 "
b111111111000000000011101 '
b11101 !
b11101 ,
b111000 +
1#
#3780000
0#
#3790000
b111001 +
b111111111000000000100110 "
b111111111000000000100110 '
b100110 !
b100110 ,
1#
#3800000
0#
#3810000
b111111111000000000101111 "
b111111111000000000101111 '
b101111 !
b101111 ,
b111010 +
1#
#3820000
0#
#3830000
b111011 +
b111111111000000000111001 "
b111111111000000000111001 '
b111001 !
b111001 ,
1#
#3840000
0#
#3850000
b111111111000000001000100 "
b111111111000000001000100 '
b1000100 !
b1000100 ,
b111100 +
1#
#3860000
0#
#3870000
b111101 +
b111111111000000001001111 "
b111111111000000001001111 '
b1001111 !
b1001111 ,
1#
#3880000
0#
#3890000
b111111111000000001011011 "
b111111111000000001011011 '
b1011011 !
b1011011 ,
b111110 +
1#
#3900000
0#
#3910000
b111111 +
b111111111000000001100111 "
b111111111000000001100111 '
b1100111 !
b1100111 ,
1#
#3920000
0#
#3930000
b111111111000000001110011 "
b111111111000000001110011 '
b1110011 !
b1110011 ,
b0 +
1#
#3940000
0#
#3950000
b1 +
b111111110111111110000000 "
b111111110111111110000000 '
b10000000 !
b10000000 ,
1#
#3960000
0#
#3970000
b111111110111111110001100 "
b111111110111111110001100 '
b10001100 !
b10001100 ,
b10 +
1#
#3980000
0#
#3990000
b11 +
b111111110111111110011000 "
b111111110111111110011000 '
b10011000 !
b10011000 ,
1#
#4000000
0#
#4010000
b111111110111111110100100 "
b111111110111111110100100 '
b10100100 !
b10100100 ,
b100 +
1#
#4020000
0#
#4030000
b101 +
b111111110111111110110000 "
b111111110111111110110000 '
b10110000 !
b10110000 ,
1#
#4040000
0#
#4050000
b111111110111111110111011 "
b111111110111111110111011 '
b10111011 !
b10111011 ,
b110 +
1#
#4060000
0#
#4070000
b111 +
b111111110111111111000110 "
b111111110111111111000110 '
b11000110 !
b11000110 ,
1#
#4080000
0#
#4090000
b111111110111111111010000 "
b111111110111111111010000 '
b11010000 !
b11010000 ,
b1000 +
1#
#4100000
0#
b10 %
b10 &
#4110000
b1010 +
b111111110111111111011001 "
b111111110111111111011001 '
b11011001 !
b11011001 ,
1#
#4120000
0#
#4130000
b111111110111111111101001 "
b111111110111111111101001 '
b11101001 !
b11101001 ,
b1100 +
1#
#4140000
0#
#4150000
b1110 +
b111111110111111111110101 "
b111111110111111111110101 '
b11110101 !
b11110101 ,
1#
#4160000
0#
#4170000
b111111110111111111111100 "
b111111110111111111111100 '
b11111100 !
b11111100 ,
b10000 +
1#
#4180000
0#
#4190000
b10010 +
b111111110111111111111111 "
b111111110111111111111111 '
b11111111 !
b11111111 ,
1#
#4200000
0#
#4210000
b111111110111111111111100 "
b111111110111111111111100 '
b11111100 !
b11111100 ,
b10100 +
1#
#4220000
0#
#4230000
b10110 +
b111111110111111111110101 "
b111111110111111111110101 '
b11110101 !
b11110101 ,
1#
#4240000
0#
#4250000
b111111110111111111101001 "
b111111110111111111101001 '
b11101001 !
b11101001 ,
b11000 +
1#
#4260000
0#
#4270000
b11010 +
b111111110111111111011001 "
b111111110111111111011001 '
b11011001 !
b11011001 ,
1#
#4280000
0#
#4290000
b111111110111111111000110 "
b111111110111111111000110 '
b11000110 !
b11000110 ,
b11100 +
1#
#4300000
0#
#4310000
b11110 +
b111111110111111110110000 "
b111111110111111110110000 '
b10110000 !
b10110000 ,
1#
#4320000
0#
#4330000
b111111110111111110011000 "
b111111110111111110011000 '
b10011000 !
b10011000 ,
b100000 +
1#
#4340000
0#
#4350000
b100010 +
b111111110111111110000000 "
b111111110111111110000000 '
b10000000 !
b10000000 ,
1#
#4360000
0#
#4370000
b111111111000000001100111 "
b111111111000000001100111 '
b1100111 !
b1100111 ,
b100100 +
1#
#4380000
0#
#4390000
b100110 +
b111111111000000001001111 "
b111111111000000001001111 '
b1001111 !
b1001111 ,
1#
#4400000
0#
#4410000
b111111111000000000111001 "
b111111111000000000111001 '
b111001 !
b111001 ,
b101000 +
1#
#4420000
0#
#4430000
b101010 +
b111111111000000000100110 "
b111111111000000000100110 '
b100110 !
b100110 ,
1#
#4440000
0#
#4450000
b111111111000000000010110 "
b111111111000000000010110 '
b10110 !
b10110 ,
b101100 +
1#
#4460000
0#
#4470000
b101110 +
b111111111000000000001010 "
b111111111000000000001010 '
b1010 !
b1010 ,
1#
#4480000
0#
#4490000
b111111111000000000000011 "
b111111111000000000000011 '
b11 !
b11 ,
b110000 +
1#
#4500000
0#
#4510000
b110010 +
b111111111000000000000001 "
b111111111000000000000001 '
b1 !
b1 ,
1#
#4520000
0#
#4530000
b111111111000000000000011 "
b111111111000000000000011 '
b11 !
b11 ,
b110100 +
1#
#4540000
0#
#4550000
b110110 +
b111111111000000000001010 "
b111111111000000000001010 '
b1010 !
b1010 ,
1#
#4560000
0#
#4570000
b111111111000000000010110 "
b111111111000000000010110 '
b10110 !
b10110 ,
b111000 +
1#
#4580000
0#
