content/code/1stCode/piso_shift_register.v
//=============================================
// 8-bit Parallel-In Serial-Out Shift Register
// Based on SN74LS165
//=============================================
module piso_shift_register (
    input wire clk,               // clock input
    input wire clk_inh,           // clock inhibit
    input wire ser,               // serial input
    input wire sh_ld_n,           // shift/load control (active low)
    input wire [7:0] parallel_in, // parallel input
    output wire qh,               // serial output (LSB)
    output wire [7:0] q           // internal register outputs
);

    reg [7:0] shift_reg;

    // Asynchronous parallel load
    always @(*) begin
        if (~sh_ld_n) begin
            shift_reg = parallel_in;   // immediate load
        end
    end

    // Shifting (on rising edge of CLK if enabled)
    always @(posedge clk) begin
        if (sh_ld_n && !clk_inh) begin
            shift_reg <= {ser, shift_reg[7:1]};
        end
    end

    // Outputs
    assign q = shift_reg;
    assign qh = shift_reg[0];  // LSB is serial output

endmodule

content/code/1stCode/tb_piso_shift_register.v
`timescale 1ns/1ps

module tb_piso_shift_register;

    reg clk;
    reg clk_inh;
    reg ser;
    reg sh_ld_n;
    reg [7:0] parallel_in;
    wire qh;
    wire [7:0] q;

    // Instantiate DUT
    piso_shift_register dut (
        .clk(clk),
        .clk_inh(clk_inh),
        .ser(ser),
        .sh_ld_n(sh_ld_n),
        .parallel_in(parallel_in),
        .qh(qh),
        .q(q)
    );

    // Clock generation
    initial begin
        clk = 0;
        forever #5 clk = ~clk; // 100MHz clock period = 10ns
    end

    initial begin
        $display("=== Parallel-In Serial-Out Shift Register Test ===");

        // Initialize
        clk_inh = 0;
        ser = 0;
        sh_ld_n = 1;
        parallel_in = 8'b00000000;

        // 1) Parallel load
        #2 sh_ld_n = 0;
        parallel_in = 8'b10110110;
        #2 sh_ld_n = 1;  // release load
        $display("Loaded value = %b", q);

        // 2) Shift 8 cycles
        repeat (8) @(posedge clk);
        $display("After shifting = %b", q);

        // 3) Clock inhibit test
        clk_inh = 1;
        ser = 1;
        @(posedge clk); // should not shift
        $display("With inhibit, reg = %b", q);

        // 4) Enable again, shift with serial input = 1
        clk_inh = 0;
        repeat (4) @(posedge clk);
        $display("After shifting in 1s, reg = %b", q);

        #20 $finish;
    end

    // Monitor for debugging
    initial begin
        $monitor("Time=%0t | SH/LD=%b | INH=%b | SER=%b | Q=%b | QH=%b",
                  $time, sh_ld_n, clk_inh, ser, q, qh);
    end

    // Waveform dump
    initial begin
        $dumpfile("waves.vcd");           
        $dumpvars(0, tb_piso_shift_register); 
    end

endmodule

content/code/1stCode/waves.vcd
$date
	Thu Sep 25 18:51:47 2025
$end
$version
	Icarus Verilog
$end
$timescale
	1ps
$end
$scope module tb_piso_shift_register $end
$var wire 1 ! qh $end
$var wire 8 " q [7:0] $end
$var reg 1 # clk $end
$var reg 1 $ clk_inh $end
$var reg 8 % parallel_in [7:0] $end
$var reg 1 & ser $end
$var reg 1 ' sh_ld_n $end
$scope module dut $end
$var wire 1 # clk $end
$var wire 1 $ clk_inh $end
$var wire 8 ( parallel_in [7:0] $end
$var wire 8 ) q [7:0] $end
$var wire 1 & ser $end
$var wire 1 ' sh_ld_n $end
$var wire 1 ! qh $end
$var reg 8 * shift_reg [7:0] $end
$upscope $end
$upscope $end
$enddefinitions $end
$comment Show the parameter values. $end
$dumpall
$end
#0
$dumpvars
bx *
bx )
b0 (
1'
0&
b0 %
0$
0#
bx "
x!
$end
#2000
0!
b10110110 "
b10110110 )
b10110110 *
b10110110 %
b10110110 (
0'
#4000
1'
#5000
1!
b1011011 "
b1011011 )
b1011011 *
1#
#10000
0#
#15000
b101101 "
b101101 )
b101101 *
1#
#20000
0#
#25000
0!
b10110 "
b10110 )
b10110 *
1#
#30000
0#
#35000
1!
b1011 "
b1011 )
b1011 *
1#
#40000
0#
#45000
b101 "
b101 )
b101 *
1#
#50000
0#
#55000
0!
b10 "
b10 )
b10 *
1#
#60000
0#
#65000
1!
b1 "
b1 )
b1 *
1#
#70000
0#
#75000
0!
b0 "
b0 )
b0 *
1&
1$
1#
#80000
0#
#85000
b10000000 "
b10000000 )
b10000000 *
0$
1#
#90000
0#
#95000
b11000000 "
b11000000 )
b11000000 *
1#
#100000
0#
#105000
b11100000 "
b11100000 )
b11100000 *
1#
#110000
0#
#115000
b11110000 "
b11110000 )
b11110000 *
1#
#120000
0#
#125000
b11111000 "
b11111000 )
b11111000 *
1#
#130000
0#
#135000
b11111100 "
b11111100 )
b11111100 *
1#
#140000
0#
#145000
b11111110 "
b11111110 )
b11111110 *
1#
