devEnv/work/2cndAssignment/src/baud_gen.v
`timescale 1ns/1ps

module baud_gen #(
    parameter integer CLK_FREQ_HZ = 25_000_000,
    parameter integer BAUD_RATE   = 115_200
) (
    input  wire clk,
    input  wire rst_n,
    input  wire en,
    input  wire align,
    output reg  tick
);
    localparam integer HALF_PERIOD = CLK_FREQ_HZ / 2;

    reg [31:0] phase_accum;
    reg [32:0] next_phase;

    always @(posedge clk or negedge rst_n) begin
        if (!rst_n) begin
            phase_accum <= 32'd0;
            tick        <= 1'b0;
        end else begin
            tick <= 1'b0;

            if (!en) begin
                phase_accum <= 32'd0;
            end else if (align) begin
                phase_accum <= HALF_PERIOD;
            end else begin
                // Accumulate baud increments and emit a tick whenever the accumulator wraps.
                // This fractional-N approach keeps long-term frequency error close to zero.
                next_phase = phase_accum + BAUD_RATE;

                if (next_phase >= CLK_FREQ_HZ) begin
                    tick        <= 1'b1;
                    phase_accum <= next_phase - CLK_FREQ_HZ;
                end else begin
                    phase_accum <= next_phase[31:0];
                end
            end
        end
    end
endmodule

devEnv/work/2cndAssignment/tb/tb_baud_gen.v
`timescale 1ns/1ps

module tb_baud_gen;
    localparam integer CLK_FREQ_HZ = 1_000_000;
    localparam integer BAUD_RATE   = 115_200;

    reg clk = 1'b0;
    reg rst_n = 1'b0;
    reg en = 1'b0;
    reg align = 1'b0;
    wire tick;

    real target_interval;
    real half_interval;
    real first_diff;
    integer cycle_count;
    integer last_tick_cycle;
    integer first_interval;
    integer interval_sum;
    integer interval_count;
    integer min_interval;
    integer max_interval;
    reg tick_prev;

    baud_gen #(
        .CLK_FREQ_HZ (CLK_FREQ_HZ),
        .BAUD_RATE   (BAUD_RATE)
    ) dut (
        .clk   (clk),
        .rst_n (rst_n),
        .en    (en),
        .align (align),
        .tick  (tick)
    );

    always #20 clk = ~clk;  // 25 MHz notional period.

    always @(posedge clk or negedge rst_n) begin
        if (!rst_n) begin
            cycle_count <= 0;
            tick_prev   <= 1'b0;
        end else begin
            cycle_count <= cycle_count + 1;
            tick_prev   <= tick;

            if (tick_prev && tick) begin
                $fatal(1, "[%0t] Tick width longer than 1 cycle detected.", $time);
            end
        end
    end

    always @(posedge clk) begin
        if (tick) begin
            integer interval;
            interval = cycle_count - last_tick_cycle;

            if (interval_count == 0) begin
                first_interval = interval;
            end else begin
                interval_sum += interval;
                if (interval < min_interval) min_interval = interval;
                if (interval > max_interval) max_interval = interval;
            end

            last_tick_cycle = cycle_count;
            interval_count  = interval_count + 1;

            if (interval_count == 40) begin
                real avg_interval;
                avg_interval = interval_sum / real'(interval_count - 1);

                if (avg_interval < target_interval - 0.1 || avg_interval > target_interval + 0.1) begin
                    $fatal(1, "Average interval %0f deviates from expected %0f cycles.", avg_interval, target_interval);
                end

                if (min_interval < $floor(target_interval) - 1 || max_interval > $ceil(target_interval) + 1) begin
                    $fatal(1, "Interval bounds out of range. min=%0d max=%0d target=%0f", min_interval, max_interval, target_interval);
                end

                half_interval = target_interval / 2.0;
                first_diff    = first_interval - half_interval;
                if (first_diff < 0) first_diff = -first_diff;
                if (first_diff > 3.0) begin
                    $fatal(1, "First interval (%0d) deviates more than 3 cycles from half-bit (%0f).", first_interval, half_interval);
                end

                en <= 1'b0;
            end
        end
    end

    initial begin
        target_interval = real'(CLK_FREQ_HZ) / real'(BAUD_RATE);
        last_tick_cycle = 0;
        first_interval  = 0;
        interval_sum    = 0;
        interval_count  = 0;
        min_interval    = 1_000_000;
        max_interval    = 0;

        repeat (5) @(posedge clk);
        rst_n <= 1'b1;

        @(posedge clk);
        en    <= 1'b1;
        align <= 1'b1;
        last_tick_cycle = cycle_count;
        @(posedge clk);
        align <= 1'b0;

        // Allow collector to disable generator once checks are done.
        wait (interval_count == 40);
        repeat (10) @(posedge clk);

        if (tick) begin
            $fatal(1, "Tick asserted after generator disabled.");
        end

        $display("tb_baud_gen: PASS");
        $finish;
    end

    initial begin 
        $dumpfile("results/tb_baud_gen.vcd");
        $dumpvars(0, tb_baud_gen);
    end




endmodule

devEnv/work/2cndAssignment/results/tb_baud_gen.vcd
$date
	Wed Oct 29 18:31:50 2025
$end
$version
	Icarus Verilog
$end
$timescale
	1ps
$end
$scope module tb_baud_gen $end
$var wire 1 ! tick $end
$var parameter 32 " BAUD_RATE $end
$var parameter 32 # CLK_FREQ_HZ $end
$var reg 1 $ align $end
$var reg 1 % clk $end
$var reg 1 & en $end
$var reg 1 ' rst_n $end
$var reg 1 ( tick_prev $end
$var integer 32 ) cycle_count [31:0] $end
$var real 1 * first_diff $end
$var integer 32 + first_interval [31:0] $end
$var real 1 , half_interval $end
$var integer 32 - interval_count [31:0] $end
$var integer 32 . interval_sum [31:0] $end
$var integer 32 / last_tick_cycle [31:0] $end
$var integer 32 0 max_interval [31:0] $end
$var integer 32 1 min_interval [31:0] $end
$var real 1 2 target_interval $end
$scope module dut $end
$var wire 1 $ align $end
$var wire 1 % clk $end
$var wire 1 & en $end
$var wire 1 ' rst_n $end
$var parameter 32 3 BAUD_RATE $end
$var parameter 32 4 CLK_FREQ_HZ $end
$var parameter 32 5 HALF_PERIOD $end
$var reg 33 6 next_phase [32:0] $end
$var reg 32 7 phase_accum [31:0] $end
$var reg 1 ! tick $end
$upscope $end
$scope begin $unm_blk_6 $end
$var integer 32 8 interval [31:0] $end
$scope begin $unm_blk_9 $end
$var real 1 9 avg_interval $end
$upscope $end
$upscope $end
$upscope $end
$enddefinitions $end
$comment Show the parameter values. $end
$dumpall
b1111010000100100000 5
b11110100001001000000 4
b11100001000000000 3
b11110100001001000000 #
b11100001000000000 "
$end
#0
$dumpvars
r0 9
bx 8
bx 7
bx 6
r8.680555555555555 2
b11110100001001000000 1
b0 0
b0 /
b0 .
b0 -
r0 ,
b0 +
r0 *
bx )
x(
0'
0&
0%
0$
x!
$end
#20000
0!
b0 7
0(
b0 )
1%
#40000
0%
#60000
1%
#80000
0%
#100000
1%
#120000
0%
#140000
1%
#160000
0%
#180000
1'
1%
#200000
0%
#220000
b1 )
1$
1&
1%
#240000
0%
#260000
b1111010000100100000 7
b10 )
0$
1%
#280000
0%
#300000
b11 )
b10010110001100100000 7
b10010110001100100000 6
1%
#320000
0%
#340000
b10110010010100100000 7
b100 )
b10110010010100100000 6
1%
#360000
0%
#380000
b101 )
b11001110011100100000 7
b11001110011100100000 6
1%
#400000
0%
#420000
b11101010100100100000 7
b110 )
b11101010100100100000 6
1%
#440000
0%
#460000
b111 )
b10010100011100000 7
1!
b100000110101100100000 6
1%
#480000
0%
#500000
b101110101011100000 7
0!
1(
b1000 )
b101110101011100000 6
b1 -
b111 /
b111 +
b111 8
1%
#520000
0%
#540000
0(
b1001 )
b1001010110011100000 7
b1001010110011100000 6
1%
#560000
0%
#580000
b1100110111011100000 7
b1010 )
b1100110111011100000 6
1%
#600000
0%
#620000
b1011 )
b10000011000011100000 7
b10000011000011100000 6
1%
#640000
0%
#660000
b10011111001011100000 7
b1100 )
b10011111001011100000 6
1%
#680000
0%
#700000
b1101 )
b10111011010011100000 7
b10111011010011100000 6
1%
#720000
0%
#740000
b11010111011011100000 7
b1110 )
b11010111011011100000 6
1%
#760000
0%
#780000
b1111 )
b11110011100011100000 7
b11110011100011100000 6
1%
#800000
0%
#820000
b11011100010100000 7
1!
b10000 )
b100001111101011100000 6
1%
#840000
0%
#860000
1(
b10001 )
b110111101010100000 7
0!
b110111101010100000 6
b10 -
b10000 /
b1001 0
b1001 1
b1001 .
b1001 8
1%
#880000
0%
#900000
b1010011110010100000 7
0(
b10010 )
b1010011110010100000 6
1%
#920000
0%
#940000
b10011 )
b1101111111010100000 7
b1101111111010100000 6
1%
#960000
0%
#980000
b10001100000010100000 7
b10100 )
b10001100000010100000 6
1%
#1000000
0%
#1020000
b10101 )
b10101000001010100000 7
b10101000001010100000 6
1%
#1040000
0%
#1060000
b11000100010010100000 7
b10110 )
b11000100010010100000 6
1%
#1080000
0%
#1100000
b10111 )
b11100000011010100000 7
b11100000011010100000 6
1%
#1120000
0%
#1140000
b1000011001100000 7
1!
b11000 )
b11111100100010100000 6
1%
#1160000
0%
#1180000
1(
b11001 )
b100100100001100000 7
0!
b100100100001100000 6
b11 -
b11000 /
b1000 1
b10001 .
b1000 8
1%
#1200000
0%
#1220000
b1000000101001100000 7
0(
b11010 )
b1000000101001100000 6
1%
#1240000
0%
#1260000
b11011 )
b1011100110001100000 7
b1011100110001100000 6
1%
#1280000
0%
#1300000
b1111000111001100000 7
b11100 )
b1111000111001100000 6
1%
#1320000
0%
#1340000
b11101 )
b10010101000001100000 7
b10010101000001100000 6
1%
#1360000
0%
#1380000
b10110001001001100000 7
b11110 )
b10110001001001100000 6
1%
#1400000
0%
#1420000
b11111 )
b11001101010001100000 7
b11001101010001100000 6
1%
#1440000
0%
#1460000
b11101001011001100000 7
b100000 )
b11101001011001100000 6
1%
#1480000
0%
#1500000
b100001 )
b10001011000100000 7
1!
b100000101100001100000 6
1%
#1520000
0%
#1540000
b101101100000100000 7
0!
1(
b100010 )
b101101100000100000 6
b100 -
b100001 /
b11010 .
b1001 8
1%
#1560000
0%
#1580000
0(
b100011 )
b1001001101000100000 7
b1001001101000100000 6
1%
#1600000
0%
#1620000
b1100101110000100000 7
b100100 )
b1100101110000100000 6
1%
#1640000
0%
#1660000
b100101 )
b10000001111000100000 7
b10000001111000100000 6
1%
#1680000
0%
#1700000
b10011110000000100000 7
b100110 )
b10011110000000100000 6
1%
#1720000
0%
#1740000
b100111 )
b10111010001000100000 7
b10111010001000100000 6
1%
#1760000
0%
#1780000
b11010110010000100000 7
b101000 )
b11010110010000100000 6
1%
#1800000
0%
#1820000
b101001 )
b11110010011000100000 7
b11110010011000100000 6
1%
#1840000
0%
#1860000
b11010010111100000 7
1!
b101010 )
b100001110100000100000 6
1%
#1880000
0%
#1900000
1(
b101011 )
b110110011111100000 7
0!
b110110011111100000 6
b101 -
b101010 /
b100011 .
1%
#1920000
0%
#1940000
b1010010100111100000 7
0(
b101100 )
b1010010100111100000 6
1%
#1960000
0%
#1980000
b101101 )
b1101110101111100000 7
b1101110101111100000 6
1%
#2000000
0%
#2020000
b10001010110111100000 7
b101110 )
b10001010110111100000 6
1%
#2040000
0%
#2060000
b101111 )
b10100110111111100000 7
b10100110111111100000 6
1%
#2080000
0%
#2100000
b11000011000111100000 7
b110000 )
b11000011000111100000 6
1%
#2120000
0%
#2140000
b110001 )
b11011111001111100000 7
b11011111001111100000 6
1%
#2160000
0%
#2180000
b111001110100000 7
1!
b110010 )
b11111011010111100000 6
1%
#2200000
0%
#2220000
1(
b110011 )
b100011010110100000 7
0!
b100011010110100000 6
b110 -
b110010 /
b101011 .
b1000 8
1%
#2240000
0%
#2260000
b111111011110100000 7
0(
b110100 )
b111111011110100000 6
1%
#2280000
0%
#2300000
b110101 )
b1011011100110100000 7
b1011011100110100000 6
1%
#2320000
0%
#2340000
b1110111101110100000 7
b110110 )
b1110111101110100000 6
1%
#2360000
0%
#2380000
b110111 )
b10010011110110100000 7
b10010011110110100000 6
1%
#2400000
0%
#2420000
b10101111111110100000 7
b111000 )
b10101111111110100000 6
1%
#2440000
0%
#2460000
b111001 )
b11001100000110100000 7
b11001100000110100000 6
1%
#2480000
0%
#2500000
b11101000001110100000 7
b111010 )
b11101000001110100000 6
1%
#2520000
0%
#2540000
b111011 )
b10000001101100000 7
1!
b100000100010110100000 6
1%
#2560000
0%
#2580000
b101100010101100000 7
0!
1(
b111100 )
b101100010101100000 6
b111 -
b111011 /
b110100 .
b1001 8
1%
#2600000
0%
#2620000
0(
b111101 )
b1001000011101100000 7
b1001000011101100000 6
1%
#2640000
0%
#2660000
b1100100100101100000 7
b111110 )
b1100100100101100000 6
1%
#2680000
0%
#2700000
b111111 )
b10000000101101100000 7
b10000000101101100000 6
1%
#2720000
0%
#2740000
b10011100110101100000 7
b1000000 )
b10011100110101100000 6
1%
#2760000
0%
#2780000
b1000001 )
b10111000111101100000 7
b10111000111101100000 6
1%
#2800000
0%
#2820000
b11010101000101100000 7
b1000010 )
b11010101000101100000 6
1%
#2840000
0%
#2860000
b1000011 )
b11110001001101100000 7
b11110001001101100000 6
1%
#2880000
0%
#2900000
b11001001100100000 7
1!
b1000100 )
b100001101010101100000 6
1%
#2920000
0%
#2940000
1(
b1000101 )
b110101010100100000 7
0!
b110101010100100000 6
b1000 -
b1000100 /
b111101 .
1%
#2960000
0%
#2980000
b1010001011100100000 7
0(
b1000110 )
b1010001011100100000 6
1%
#3000000
0%
#3020000
b1000111 )
b1101101100100100000 7
b1101101100100100000 6
1%
#3040000
0%
#3060000
b10001001101100100000 7
b1001000 )
b10001001101100100000 6
1%
#3080000
0%
#3100000
b1001001 )
b10100101110100100000 7
b10100101110100100000 6
1%
#3120000
0%
#3140000
b11000001111100100000 7
b1001010 )
b11000001111100100000 6
1%
#3160000
0%
#3180000
b1001011 )
b11011110000100100000 7
b11011110000100100000 6
1%
#3200000
0%
#3220000
b110000011100000 7
1!
b1001100 )
b11111010001100100000 6
1%
#3240000
0%
#3260000
1(
b1001101 )
b100010001011100000 7
0!
b100010001011100000 6
b1001 -
b1001100 /
b1000101 .
b1000 8
1%
#3280000
0%
#3300000
b111110010011100000 7
0(
b1001110 )
b111110010011100000 6
1%
#3320000
0%
#3340000
b1001111 )
b1011010011011100000 7
b1011010011011100000 6
1%
#3360000
0%
#3380000
b1110110100011100000 7
b1010000 )
b1110110100011100000 6
1%
#3400000
0%
#3420000
b1010001 )
b10010010101011100000 7
b10010010101011100000 6
1%
#3440000
0%
#3460000
b10101110110011100000 7
b1010010 )
b10101110110011100000 6
1%
#3480000
0%
#3500000
b1010011 )
b11001010111011100000 7
b11001010111011100000 6
1%
#3520000
0%
#3540000
b11100111000011100000 7
b1010100 )
b11100111000011100000 6
1%
#3560000
0%
#3580000
b1010101 )
b1111000010100000 7
1!
b100000011001011100000 6
1%
#3600000
0%
#3620000
b101011001010100000 7
0!
1(
b1010110 )
b101011001010100000 6
b1010 -
b1010101 /
b1001110 .
b1001 8
1%
#3640000
0%
#3660000
0(
b1010111 )
b1000111010010100000 7
b1000111010010100000 6
1%
#3680000
0%
#3700000
b1100011011010100000 7
b1011000 )
b1100011011010100000 6
1%
#3720000
0%
#3740000
b1011001 )
b1111111100010100000 7
b1111111100010100000 6
1%
#3760000
0%
#3780000
b10011011101010100000 7
b1011010 )
b10011011101010100000 6
1%
#3800000
0%
#3820000
b1011011 )
b10110111110010100000 7
b10110111110010100000 6
1%
#3840000
0%
#3860000
b11010011111010100000 7
b1011100 )
b11010011111010100000 6
1%
#3880000
0%
#3900000
b1011101 )
b11110000000010100000 7
b11110000000010100000 6
1%
#3920000
0%
#3940000
b11000000001100000 7
1!
b1011110 )
b100001100001010100000 6
1%
#3960000
0%
#3980000
1(
b1011111 )
b110100001001100000 7
0!
b110100001001100000 6
b1011 -
b1011110 /
b1010111 .
1%
#4000000
0%
#4020000
b1010000010001100000 7
0(
b1100000 )
b1010000010001100000 6
1%
#4040000
0%
#4060000
b1100001 )
b1101100011001100000 7
b1101100011001100000 6
1%
#4080000
0%
#4100000
b10001000100001100000 7
b1100010 )
b10001000100001100000 6
1%
#4120000
0%
#4140000
b1100011 )
b10100100101001100000 7
b10100100101001100000 6
1%
#4160000
0%
#4180000
b11000000110001100000 7
b1100100 )
b11000000110001100000 6
1%
#4200000
0%
#4220000
b1100101 )
b11011100111001100000 7
b11011100111001100000 6
1%
#4240000
0%
#4260000
b100111000100000 7
1!
b1100110 )
b11111001000001100000 6
1%
#4280000
0%
#4300000
1(
b1100111 )
b100001000000100000 7
0!
b100001000000100000 6
b1100 -
b1100110 /
b1011111 .
b1000 8
1%
#4320000
0%
#4340000
b111101001000100000 7
0(
b1101000 )
b111101001000100000 6
1%
#4360000
0%
#4380000
b1101001 )
b1011001010000100000 7
b1011001010000100000 6
1%
#4400000
0%
#4420000
b1110101011000100000 7
b1101010 )
b1110101011000100000 6
1%
#4440000
0%
#4460000
b1101011 )
b10010001100000100000 7
b10010001100000100000 6
1%
#4480000
0%
#4500000
b10101101101000100000 7
b1101100 )
b10101101101000100000 6
1%
#4520000
0%
#4540000
b1101101 )
b11001001110000100000 7
b11001001110000100000 6
1%
#4560000
0%
#4580000
b11100101111000100000 7
b1101110 )
b11100101111000100000 6
1%
#4600000
0%
#4620000
b1101111 )
b1101110111100000 7
1!
b100000010000000100000 6
1%
#4640000
0%
#4660000
b101001111111100000 7
0!
1(
b1110000 )
b101001111111100000 6
b1101 -
b1101111 /
b1101000 .
b1001 8
1%
#4680000
0%
#4700000
0(
b1110001 )
b1000110000111100000 7
b1000110000111100000 6
1%
#4720000
0%
#4740000
b1100010001111100000 7
b1110010 )
b1100010001111100000 6
1%
#4760000
0%
#4780000
b1110011 )
b1111110010111100000 7
b1111110010111100000 6
1%
#4800000
0%
#4820000
b10011010011111100000 7
b1110100 )
b10011010011111100000 6
1%
#4840000
0%
#4860000
b1110101 )
b10110110100111100000 7
b10110110100111100000 6
1%
#4880000
0%
#4900000
b11010010101111100000 7
b1110110 )
b11010010101111100000 6
1%
#4920000
0%
#4940000
b1110111 )
b11101110110111100000 7
b11101110110111100000 6
1%
#4960000
0%
#4980000
b10110110110100000 7
1!
b1111000 )
b100001010111111100000 6
1%
#5000000
0%
#5020000
1(
b1111001 )
b110010111110100000 7
0!
b110010111110100000 6
b1110 -
b1111000 /
b1110001 .
1%
#5040000
0%
#5060000
b1001111000110100000 7
0(
b1111010 )
b1001111000110100000 6
1%
#5080000
0%
#5100000
b1111011 )
b1101011001110100000 7
b1101011001110100000 6
1%
#5120000
0%
#5140000
b10000111010110100000 7
b1111100 )
b10000111010110100000 6
1%
#5160000
0%
#5180000
b1111101 )
b10100011011110100000 7
b10100011011110100000 6
1%
#5200000
0%
#5220000
b10111111100110100000 7
b1111110 )
b10111111100110100000 6
1%
#5240000
0%
#5260000
b1111111 )
b11011011101110100000 7
b11011011101110100000 6
1%
#5280000
0%
#5300000
b11101101100000 7
1!
b10000000 )
b11110111110110100000 6
1%
#5320000
0%
#5340000
1(
b10000001 )
b11111110101100000 7
0!
b11111110101100000 6
b1111 -
b10000000 /
b1111001 .
b1000 8
1%
#5360000
0%
#5380000
b111011111101100000 7
0(
b10000010 )
b111011111101100000 6
1%
#5400000
0%
#5420000
b10000011 )
b1011000000101100000 7
b1011000000101100000 6
1%
#5440000
0%
#5460000
b1110100001101100000 7
b10000100 )
b1110100001101100000 6
1%
#5480000
0%
#5500000
b10000101 )
b10010000010101100000 7
b10010000010101100000 6
1%
#5520000
0%
#5540000
b10101100011101100000 7
b10000110 )
b10101100011101100000 6
1%
#5560000
0%
#5580000
b10000111 )
b11001000100101100000 7
b11001000100101100000 6
1%
#5600000
0%
#5620000
b11100100101101100000 7
b10001000 )
b11100100101101100000 6
1%
#5640000
0%
#5660000
b10001001 )
b1100101100100000 7
1!
b100000000110101100000 6
1%
#5680000
0%
#5700000
b101000110100100000 7
0!
1(
b10001010 )
b101000110100100000 6
b10000 -
b10001001 /
b10000010 .
b1001 8
1%
#5720000
0%
#5740000
0(
b10001011 )
b1000100111100100000 7
b1000100111100100000 6
1%
#5760000
0%
#5780000
b1100001000100100000 7
b10001100 )
b1100001000100100000 6
1%
#5800000
0%
#5820000
b10001101 )
b1111101001100100000 7
b1111101001100100000 6
1%
#5840000
0%
#5860000
b10011001010100100000 7
b10001110 )
b10011001010100100000 6
1%
#5880000
0%
#5900000
b10001111 )
b10110101011100100000 7
b10110101011100100000 6
1%
#5920000
0%
#5940000
b11010001100100100000 7
b10010000 )
b11010001100100100000 6
1%
#5960000
0%
#5980000
b10010001 )
b11101101101100100000 7
b11101101101100100000 6
1%
#6000000
0%
#6020000
b10101101011100000 7
1!
b10010010 )
b100001001110100100000 6
1%
#6040000
0%
#6060000
1(
b10010011 )
b110001110011100000 7
0!
b110001110011100000 6
b10001 -
b10010010 /
b10001011 .
1%
#6080000
0%
#6100000
b1001101111011100000 7
0(
b10010100 )
b1001101111011100000 6
1%
#6120000
0%
#6140000
b10010101 )
b1101010000011100000 7
b1101010000011100000 6
1%
#6160000
0%
#6180000
b10000110001011100000 7
b10010110 )
b10000110001011100000 6
1%
#6200000
0%
#6220000
b10010111 )
b10100010010011100000 7
b10100010010011100000 6
1%
#6240000
0%
#6260000
b10111110011011100000 7
b10011000 )
b10111110011011100000 6
1%
#6280000
0%
#6300000
b10011001 )
b11011010100011100000 7
b11011010100011100000 6
1%
#6320000
0%
#6340000
b10100010100000 7
1!
b10011010 )
b11110110101011100000 6
1%
#6360000
0%
#6380000
1(
b10011011 )
b11110101010100000 7
0!
b11110101010100000 6
b10010 -
b10011010 /
b10010011 .
b1000 8
1%
#6400000
0%
#6420000
b111010110010100000 7
0(
b10011100 )
b111010110010100000 6
1%
#6440000
0%
#6460000
b10011101 )
b1010110111010100000 7
b1010110111010100000 6
1%
#6480000
0%
#6500000
b1110011000010100000 7
b10011110 )
b1110011000010100000 6
1%
#6520000
0%
#6540000
b10011111 )
b10001111001010100000 7
b10001111001010100000 6
1%
#6560000
0%
#6580000
b10101011010010100000 7
b10100000 )
b10101011010010100000 6
1%
#6600000
0%
#6620000
b10100001 )
b11000111011010100000 7
b11000111011010100000 6
1%
#6640000
0%
#6660000
b11100011100010100000 7
b10100010 )
b11100011100010100000 6
1%
#6680000
0%
#6700000
b10100011 )
b1011100001100000 7
1!
b11111111101010100000 6
1%
#6720000
0%
#6740000
b100111101001100000 7
0!
1(
b10100100 )
b100111101001100000 6
b10011 -
b10100011 /
b10011100 .
b1001 8
1%
#6760000
0%
#6780000
0(
b10100101 )
b1000011110001100000 7
b1000011110001100000 6
1%
#6800000
0%
#6820000
b1011111111001100000 7
b10100110 )
b1011111111001100000 6
1%
#6840000
0%
#6860000
b10100111 )
b1111100000001100000 7
b1111100000001100000 6
1%
#6880000
0%
#6900000
b10011000001001100000 7
b10101000 )
b10011000001001100000 6
1%
#6920000
0%
#6940000
b10101001 )
b10110100010001100000 7
b10110100010001100000 6
1%
#6960000
0%
#6980000
b11010000011001100000 7
b10101010 )
b11010000011001100000 6
1%
#7000000
0%
#7020000
b10101011 )
b11101100100001100000 7
b11101100100001100000 6
1%
#7040000
0%
#7060000
b10100100000100000 7
1!
b10101100 )
b100001000101001100000 6
1%
#7080000
0%
#7100000
1(
b10101101 )
b110000101000100000 7
0!
b110000101000100000 6
b10100 -
b10101100 /
b10100101 .
1%
#7120000
0%
#7140000
b1001100110000100000 7
0(
b10101110 )
b1001100110000100000 6
1%
#7160000
0%
#7180000
b10101111 )
b1101000111000100000 7
b1101000111000100000 6
1%
#7200000
0%
#7220000
b10000101000000100000 7
b10110000 )
b10000101000000100000 6
1%
#7240000
0%
#7260000
b10110001 )
b10100001001000100000 7
b10100001001000100000 6
1%
#7280000
0%
#7300000
b10111101010000100000 7
b10110010 )
b10111101010000100000 6
1%
#7320000
0%
#7340000
b10110011 )
b11011001011000100000 7
b11011001011000100000 6
1%
#7360000
0%
#7380000
b1010111100000 7
1!
b10110100 )
b11110101100000100000 6
1%
#7400000
0%
#7420000
1(
b10110101 )
b11101011111100000 7
0!
b11101011111100000 6
b10101 -
b10110100 /
b10101101 .
b1000 8
1%
#7440000
0%
#7460000
b111001100111100000 7
0(
b10110110 )
b111001100111100000 6
1%
#7480000
0%
#7500000
b10110111 )
b1010101101111100000 7
b1010101101111100000 6
1%
#7520000
0%
#7540000
b1110001110111100000 7
b10111000 )
b1110001110111100000 6
1%
#7560000
0%
#7580000
b10111001 )
b10001101111111100000 7
b10001101111111100000 6
1%
#7600000
0%
#7620000
b10101010000111100000 7
b10111010 )
b10101010000111100000 6
1%
#7640000
0%
#7660000
b10111011 )
b11000110001111100000 7
b11000110001111100000 6
1%
#7680000
0%
#7700000
b11100010010111100000 7
b10111100 )
b11100010010111100000 6
1%
#7720000
0%
#7740000
b10111101 )
b1010010110100000 7
1!
b11111110011111100000 6
1%
#7760000
0%
#7780000
b100110011110100000 7
0!
1(
b10111110 )
b100110011110100000 6
b10110 -
b10111101 /
b10110110 .
b1001 8
1%
#7800000
0%
#7820000
0(
b10111111 )
b1000010100110100000 7
b1000010100110100000 6
1%
#7840000
0%
#7860000
b1011110101110100000 7
b11000000 )
b1011110101110100000 6
1%
#7880000
0%
#7900000
b11000001 )
b1111010110110100000 7
b1111010110110100000 6
1%
#7920000
0%
#7940000
b10010110111110100000 7
b11000010 )
b10010110111110100000 6
1%
#7960000
0%
#7980000
b11000011 )
b10110011000110100000 7
b10110011000110100000 6
1%
#8000000
0%
#8020000
b11001111001110100000 7
b11000100 )
b11001111001110100000 6
1%
#8040000
0%
#8060000
b11000101 )
b11101011010110100000 7
b11101011010110100000 6
1%
#8080000
0%
#8100000
b10011010101100000 7
1!
b11000110 )
b100000111011110100000 6
1%
#8120000
0%
#8140000
1(
b11000111 )
b101111011101100000 7
0!
b101111011101100000 6
b10111 -
b11000110 /
b10111111 .
1%
#8160000
0%
#8180000
b1001011100101100000 7
0(
b11001000 )
b1001011100101100000 6
1%
#8200000
0%
#8220000
b11001001 )
b1100111101101100000 7
b1100111101101100000 6
1%
#8240000
0%
#8260000
b10000011110101100000 7
b11001010 )
b10000011110101100000 6
1%
#8280000
0%
#8300000
b11001011 )
b10011111111101100000 7
b10011111111101100000 6
1%
#8320000
0%
#8340000
b10111100000101100000 7
b11001100 )
b10111100000101100000 6
1%
#8360000
0%
#8380000
b11001101 )
b11011000001101100000 7
b11011000001101100000 6
1%
#8400000
0%
#8420000
b1100100000 7
1!
b11001110 )
b11110100010101100000 6
1%
#8440000
0%
#8460000
1(
b11001111 )
b11100010100100000 7
0!
b11100010100100000 6
b11000 -
b11001110 /
b11000111 .
b1000 8
1%
#8480000
0%
#8500000
b111000011100100000 7
0(
b11010000 )
b111000011100100000 6
1%
#8520000
0%
#8540000
b11010001 )
b1010100100100100000 7
b1010100100100100000 6
1%
#8560000
0%
#8580000
b1110000101100100000 7
b11010010 )
b1110000101100100000 6
1%
#8600000
0%
#8620000
b11010011 )
b10001100110100100000 7
b10001100110100100000 6
1%
#8640000
0%
#8660000
b10101000111100100000 7
b11010100 )
b10101000111100100000 6
1%
#8680000
0%
#8700000
b11010101 )
b11000101000100100000 7
b11000101000100100000 6
1%
#8720000
0%
#8740000
b11100001001100100000 7
b11010110 )
b11100001001100100000 6
1%
#8760000
0%
#8780000
b11010111 )
b1001001011100000 7
1!
b11111101010100100000 6
1%
#8800000
0%
#8820000
b100101010011100000 7
0!
1(
b11011000 )
b100101010011100000 6
b11001 -
b11010111 /
b11010000 .
b1001 8
1%
#8840000
0%
#8860000
0(
b11011001 )
b1000001011011100000 7
b1000001011011100000 6
1%
#8880000
0%
#8900000
b1011101100011100000 7
b11011010 )
b1011101100011100000 6
1%
#8920000
0%
#8940000
b11011011 )
b1111001101011100000 7
b1111001101011100000 6
1%
#8960000
0%
#8980000
b10010101110011100000 7
b11011100 )
b10010101110011100000 6
1%
#9000000
0%
#9020000
b11011101 )
b10110001111011100000 7
b10110001111011100000 6
1%
#9040000
0%
#9060000
b11001110000011100000 7
b11011110 )
b11001110000011100000 6
1%
#9080000
0%
#9100000
b11011111 )
b11101010001011100000 7
b11101010001011100000 6
1%
#9120000
0%
#9140000
b10010001010100000 7
1!
b11100000 )
b100000110010011100000 6
1%
#9160000
0%
#9180000
1(
b11100001 )
b101110010010100000 7
0!
b101110010010100000 6
b11010 -
b11100000 /
b11011001 .
1%
#9200000
0%
#9220000
b1001010011010100000 7
0(
b11100010 )
b1001010011010100000 6
1%
#9240000
0%
#9260000
b11100011 )
b1100110100010100000 7
b1100110100010100000 6
1%
#9280000
0%
#9300000
b10000010101010100000 7
b11100100 )
b10000010101010100000 6
1%
#9320000
0%
#9340000
b11100101 )
b10011110110010100000 7
b10011110110010100000 6
1%
#9360000
0%
#9380000
b10111010111010100000 7
b11100110 )
b10111010111010100000 6
1%
#9400000
0%
#9420000
b11100111 )
b11010111000010100000 7
b11010111000010100000 6
1%
#9440000
0%
#9460000
b11110011001010100000 7
b11101000 )
b11110011001010100000 6
1%
#9480000
0%
#9500000
b11101001 )
b11011001001100000 7
1!
b100001111010010100000 6
1%
#9520000
0%
#9540000
b110111010001100000 7
0!
1(
b11101010 )
b110111010001100000 6
b11011 -
b11101001 /
b11100010 .
1%
#9560000
0%
#9580000
0(
b11101011 )
b1010011011001100000 7
b1010011011001100000 6
1%
#9600000
0%
#9620000
b1101111100001100000 7
b11101100 )
b1101111100001100000 6
1%
#9640000
0%
#9660000
b11101101 )
b10001011101001100000 7
b10001011101001100000 6
1%
#9680000
0%
#9700000
b10100111110001100000 7
b11101110 )
b10100111110001100000 6
1%
#9720000
0%
#9740000
b11101111 )
b11000011111001100000 7
b11000011111001100000 6
1%
#9760000
0%
#9780000
b11100000000001100000 7
b11110000 )
b11100000000001100000 6
1%
#9800000
0%
#9820000
b11110001 )
b1000000000100000 7
1!
b11111100001001100000 6
1%
#9840000
0%
#9860000
b100100001000100000 7
0!
1(
b11110010 )
b100100001000100000 6
b11100 -
b11110001 /
b11101010 .
b1000 8
1%
#9880000
0%
#9900000
0(
b11110011 )
b1000000010000100000 7
b1000000010000100000 6
1%
#9920000
0%
#9940000
b1011100011000100000 7
b11110100 )
b1011100011000100000 6
1%
#9960000
0%
#9980000
b11110101 )
b1111000100000100000 7
b1111000100000100000 6
1%
#10000000
0%
#10020000
b10010100101000100000 7
b11110110 )
b10010100101000100000 6
1%
#10040000
0%
#10060000
b11110111 )
b10110000110000100000 7
b10110000110000100000 6
1%
#10080000
0%
#10100000
b11001100111000100000 7
b11111000 )
b11001100111000100000 6
1%
#10120000
0%
#10140000
b11111001 )
b11101001000000100000 7
b11101001000000100000 6
1%
#10160000
0%
