devEnv/work/1stAssignment/src/decoder3to8.v
// 3-to-8 one-hot decoder (combinational)
module decoder3to8 (
    input  wire [2:0] sel,
    output wire [7:0] y
);
    assign y = 8'b0000_0001 << sel;
endmodule

devEnv/tasks/1stTask/src/updown_counter4.v
// 4-bit up/down counter with async reset and enable
module updown_counter4 (
    input  wire       clk,
    input  wire       arst,    // asynchronous active-high reset
    input  wire       en,      // count enable
    input  wire       dir,     // 1 = up, 0 = down
    output reg  [3:0] q
);
    always @(posedge clk or posedge arst) begin
        if (arst) begin
            q <= 4'd0;
        end else if (en) begin
            if (dir) q <= q + 4'd1;
            else     q <= q - 4'd1;
        end
    end
endmodule

devEnv/tasks/1stTask/src/two_state_fsm.v
// Two-state FSM controlling direction based on position bounds
// States: RIGHT (dir=1), LEFT (dir=0)
module two_state_fsm (
    input  wire       clk,
    input  wire       arst,   // asynchronous active-high reset
    input  wire [2:0] pos,    // current position 0..7
    output reg        dir     // 1 = right/up, 0 = left/down
);
    localparam RIGHT = 1'b1;
    localparam LEFT  = 1'b0;

    // State register is 'dir' itself
    always @(posedge clk or posedge arst) begin
        if (arst) begin
            dir <= RIGHT; // start moving right by default
        end else begin
            case (dir)
                RIGHT: dir <= (pos == 3'd7) ? LEFT : RIGHT;
                LEFT:  dir <= (pos == 3'd0) ? RIGHT : LEFT;
                default: dir <= RIGHT;
            endcase
        end
    end
endmodule

devEnv/tasks/1stTask/src/top_knightrider.v
// Top module: connects FSM, counter, decoder to create Knight Rider effect
module top_knightrider (
    input  wire       clk,
    input  wire       arst,     // asynchronous active-high reset
    input  wire       en,       // enable counting/animation
    output wire [7:0] leds      // one-hot moving light
);
    wire       dir;
    wire [3:0] count;
    wire [2:0] pos = count[2:0];
    // Compute next direction combinationally to avoid boundary dwell
    wire       dir_next = dir ? ((pos == 3'd7) ? 1'b0 : 1'b1)
                              : ((pos == 3'd0) ? 1'b1 : 1'b0);
    wire       en_cnt = en; // no gating needed with dir_next

    // Direction FSM toggles at boundaries (0 and 7)
    two_state_fsm u_fsm (
        .clk (clk),
        .arst(arst),
        .pos (pos),
        .dir (dir)
    );

    // Counter uses dir; with FSM policy it never steps outside 0..7
    updown_counter4 u_cnt (
        .clk (clk),
        .arst(arst),
        .en  (en_cnt),
        .dir (dir_next),
        .q   (count)
    );

    // 3-to-8 decoder generates one-hot LEDs
    decoder3to8 u_dec (
        .sel(pos),
        .y  (leds)
    );
endmodule

devEnv/tasks/1stTask/tb/tb_top_knightrider.v
`timescale 1ns/1ps
module tb_top_knightrider;
    reg clk;
    reg arst;
    reg en;
    wire [7:0] leds;

    top_knightrider dut(
        .clk(clk), .arst(arst), .en(en), .leds(leds)
    );

    initial clk = 0; always #5 clk = ~clk; // 100MHz simulated

    // Check that pattern bounces: 0000_0001 -> ... -> 1000_0000 -> 0100_0000 -> ...
    reg [7:0] expected;
    integer i;
    initial begin
        $display("[tb_top_knightrider] Start");
        arst = 1; en = 0; @(posedge clk); #1; arst = 0; en = 1;

        // Immediately after releasing reset and enabling, LED should be at LSB
        expected = 8'b0000_0001;
        #1;
        if (leds !== expected) $fatal(1, "Initial mismatch: leds=%b exp=%b", leds, expected);

        // First ascend 1..7 (since we already checked position 0)
        expected = 8'b0000_0010;
        for (i = 1; i < 8; i = i + 1) begin
            @(posedge clk); #1;
            if (leds !== expected) $fatal(1, "Ascend mismatch at step %0d: leds=%b exp=%b", i, leds, expected);
            expected = (i < 7) ? (expected << 1) : (8'b0100_0000); // after reaching MSB, next should be one step left
        end
        // Descend 6..0
        for (i = 6; i >= 0; i = i - 1) begin
            @(posedge clk); #1;
            if (leds !== expected) $fatal(1, "Descend mismatch at pos %0d: leds=%b exp=%b", i, leds, expected);
            expected = (i > 0) ? (expected >> 1) : (8'b0000_0010); // next cycle would go right again
        end

        $display("[tb_top_knightrider] PASS");
        $finish;
    end
endmodule

devEnv/work/1stAssignment/results/tb_top_knightrider.vcd
$date
	Fri Oct 17 11:25:13 2025
$end
$version
	Icarus Verilog
$end
$timescale
	1ps
$end
$scope module tb_top_knightrider $end
$var wire 8 ! leds [7:0] $end
$var reg 1 " arst $end
$var reg 1 # clk $end
$var reg 1 $ en $end
$var reg 8 % expected [7:0] $end
$var integer 32 & i [31:0] $end
$scope module dut $end
$var wire 1 " arst $end
$var wire 1 # clk $end
$var wire 1 $ en $end
$var wire 1 ' en_cnt $end
$var wire 3 ( pos [2:0] $end
$var wire 8 ) leds [7:0] $end
$var wire 1 * dir_next $end
$var wire 1 + dir $end
$var wire 4 , count [3:0] $end
$scope module u_cnt $end
$var wire 1 " arst $end
$var wire 1 # clk $end
$var wire 1 * dir $end
$var wire 1 ' en $end
$var reg 4 - q [3:0] $end
$upscope $end
$scope module u_dec $end
$var wire 3 . sel [2:0] $end
$var wire 8 / y [7:0] $end
$upscope $end
$scope module u_fsm $end
$var wire 1 " arst $end
$var wire 1 # clk $end
$var wire 3 0 pos [2:0] $end
$var parameter 1 1 LEFT $end
$var parameter 1 2 RIGHT $end
$var reg 1 + dir $end
$upscope $end
$upscope $end
$upscope $end
$enddefinitions $end
$comment Show the parameter values. $end
$dumpall
12
01
$end
#0
$dumpvars
b0 0
b1 /
b0 .
b0 -
b0 ,
1+
1*
b1 )
b0 (
0'
bx &
bx %
0$
0#
1"
b1 !
$end
#5000
1#
#6000
b1 %
1'
1$
0"
#7000
b1 &
b10 %
#10000
0#
#15000
b10 !
b10 )
b10 /
b1 (
b1 .
b1 0
b1 ,
b1 -
1#
#16000
b10 &
b100 %
#20000
0#
#25000
b100 !
b100 )
b100 /
b10 (
b10 .
b10 0
b10 ,
b10 -
1#
#26000
b11 &
b1000 %
#30000
0#
#35000
b1000 !
b1000 )
b1000 /
b11 (
b11 .
b11 0
b11 ,
b11 -
1#
#36000
b100 &
b10000 %
#40000
0#
#45000
b10000 !
b10000 )
b10000 /
b100 (
b100 .
b100 0
b100 ,
b100 -
1#
#46000
b101 &
b100000 %
#50000
0#
#55000
b100000 !
b100000 )
b100000 /
b101 (
b101 .
b101 0
b101 ,
b101 -
1#
#56000
b110 &
b1000000 %
#60000
0#
#65000
b1000000 !
b1000000 )
b1000000 /
b110 (
b110 .
b110 0
b110 ,
b110 -
1#
#66000
b111 &
b10000000 %
#70000
0#
#75000
0*
b10000000 !
b10000000 )
b10000000 /
b111 (
b111 .
b111 0
b111 ,
b111 -
1#
#76000
b110 &
b1000000 %
#80000
0#
#85000
b1000000 !
b1000000 )
b1000000 /
b110 (
b110 .
b110 0
b110 ,
b110 -
0+
1#
#86000
b101 &
b100000 %
#90000
0#
#95000
b100000 !
b100000 )
b100000 /
b101 (
b101 .
b101 0
b101 ,
b101 -
1#
#96000
b100 &
b10000 %
#100000
0#
#105000
b10000 !
b10000 )
b10000 /
b100 (
b100 .
b100 0
b100 ,
b100 -
1#
#106000
b11 &
b1000 %
#110000
0#
#115000
b1000 !
b1000 )
b1000 /
b11 (
b11 .
b11 0
b11 ,
b11 -
1#
#116000
b10 &
b100 %
#120000
0#
#125000
b100 !
b100 )
b100 /
b10 (
b10 .
b10 0
b10 ,
b10 -
1#
#126000
b1 &
b10 %
#130000
0#
#135000
b10 !
b10 )
b10 /
b1 (
b1 .
b1 0
b1 ,
b1 -
1#
#136000
b0 &
b1 %
#140000
0#
#145000
1*
b1 !
b1 )
b1 /
b0 (
b0 .
b0 0
b0 ,
b0 -
1#
#146000
b11111111111111111111111111111111 &
b10 %
