devEnv/tasks/1stTask/src/updown_counter4.v
// 4-bit up/down counter with async reset and enable
module updown_counter4 (
    input  wire       clk,
    input  wire       arst,    // asynchronous active-high reset
    input  wire       en,      // count enable
    input  wire       dir,     // 1 = up, 0 = down
    output reg  [3:0] q
);
    always @(posedge clk or posedge arst) begin
        if (arst) begin
            q <= 4'd0;
        end else if (en) begin
            if (dir) q <= q + 4'd1;
            else     q <= q - 4'd1;
        end
    end
endmodule

devEnv/tasks/1stTask/tb/tb_updown_counter4.v
`timescale 1ns/1ps
module tb_updown_counter4;
    reg clk;
    reg arst;
    reg en;
    reg dir;
    wire [3:0] q;

    updown_counter4 dut(
        .clk(clk), .arst(arst), .en(en), .dir(dir), .q(q)
    );

    // clock
    initial clk = 0;
    always #5 clk = ~clk; // 100 MHz -> 10ns period (scaled)

    initial begin
        $display("[tb_updown_counter4] Start");
        arst = 1; en = 0; dir = 1; @(posedge clk); #1;
        if (q !== 4'd0) $fatal(1, "Reset failed");
        arst = 0; en = 1; dir = 1;
        repeat (5) @(posedge clk); #1; // allow NBA updates
        if (q !== 4'd5) $fatal(1, "Count up failed: q=%0d", q);
        dir = 0; // count down
        repeat (3) @(posedge clk); #1;
        if (q !== 4'd2) $fatal(1, "Count down failed: q=%0d", q);
        en = 0; repeat (2) @(posedge clk); #1;
        if (q !== 4'd2) $fatal(1, "Enable gating failed");
        $display("[tb_updown_counter4] PASS");
        $finish;
    end
endmodule

devEnv/work/1stAssignment/results/tb_updown_counter4.vcd
$date
	Fri Oct 17 11:25:13 2025
$end
$version
	Icarus Verilog
$end
$timescale
	1ps
$end
$scope module tb_updown_counter4 $end
$var wire 4 ! q [3:0] $end
$var reg 1 " arst $end
$var reg 1 # clk $end
$var reg 1 $ dir $end
$var reg 1 % en $end
$scope module dut $end
$var wire 1 " arst $end
$var wire 1 # clk $end
$var wire 1 $ dir $end
$var wire 1 % en $end
$var reg 4 & q [3:0] $end
$upscope $end
$upscope $end
$enddefinitions $end
$comment Show the parameter values. $end
$dumpall
$end
#0
$dumpvars
b0 &
0%
1$
0#
1"
b0 !
$end
#5000
1#
#6000
1%
0"
#10000
0#
#15000
b1 !
b1 &
1#
#20000
0#
#25000
b10 !
b10 &
1#
#30000
0#
#35000
b11 !
b11 &
1#
#40000
0#
#45000
b100 !
b100 &
1#
#50000
0#
#55000
b101 !
b101 &
1#
#56000
0$
#60000
0#
#65000
b100 !
b100 &
1#
#70000
0#
#75000
b11 !
b11 &
1#
#80000
0#
#85000
b10 !
b10 &
1#
#86000
0%
